{
  "summary": {
    "reach": 3802347,
    "impressions": 6523896,
    "frequency": 1.72,
    "spend": 805252.13,
    "clicks": 69362,
    "link_clicks": 52232,
    "ctr": 1.06,
    "cpm": 123.43,
    "cpc": 11.61,
    "landing_views": 39464,
    "cost_per_landing_view": 20.4,
    "add_to_cart": 4524,
    "cost_per_atc": 178.0,
    "initiate_checkout": 3676,
    "cost_per_initiate_checkout": 219.06,
    "conversions": 1603,
    "revenue": 1726342.11,
    "revenue_source": "shopify",
    "shopify_orders": 1603,
    "roas": 2.14,
    "cac": 502.34
  },
  "campaigns": [
    {
      "id": "120244302681680161",
      "name": "CM | Frozen Scaling | 06/04/26",
      "status": "ACTIVE",
      "objective": "OUTCOME_SALES",
      "reach": 1451729,
      "impressions": 2226871,
      "frequency": 1.53,
      "spend": 216343.52,
      "link_clicks": 19717,
      "ctr": 1.16,
      "cpm": 97.15,
      "cpc": 8.34,
      "landing_views": 15317,
      "cost_per_landing_view": 14.12,
      "atc": 1466,
      "cost_per_atc": 147.57,
      "initiate_checkout": 1212,
      "cost_per_initiate_checkout": 178.5,
      "atc_abandon_rate": 68.8,
      "checkout_abandon_rate": 62.3,
      "purchases": 457,
      "revenue": 520975.75,
      "roas": 2.41,
      "cac": 473.4,
      "funnel": {
        "reach": 1451729,
        "impressions": 2226871,
        "link_clicks": 19717,
        "landing_views": 15317,
        "add_to_cart": 1466,
        "initiate_checkout": 1212,
        "purchases": 457,
        "dropoffs": {
          "impressions_to_link_clicks": 0.89,
          "link_clicks_to_landing": 77.7,
          "landing_to_cart": 9.6,
          "cart_to_checkout": 82.7,
          "cart_to_purchase": 31.2,
          "checkout_to_purchase": 37.7
        }
      }
    },
    {
      "id": "120243993730640161",
      "name": "CM | Amazon LP | Jamun Strips & Cubes | 010426",
      "status": "ACTIVE",
      "objective": "OUTCOME_SALES",
      "reach": 13625,
      "impressions": 18654,
      "frequency": 1.37,
      "spend": 3339.69,
      "link_clicks": 301,
      "ctr": 1.57,
      "cpm": 179.03,
      "cpc": 11.4,
      "landing_views": 60,
      "cost_per_landing_view": 55.66,
      "atc": 8,
      "cost_per_atc": 417.46,
      "initiate_checkout": 3,
      "cost_per_initiate_checkout": 1113.23,
      "atc_abandon_rate": 75.0,
      "checkout_abandon_rate": 33.3,
      "purchases": 2,
      "revenue": 1755.0,
      "roas": 0.53,
      "cac": 1669.85,
      "funnel": {
        "reach": 13625,
        "impressions": 18654,
        "link_clicks": 301,
        "landing_views": 60,
        "add_to_cart": 8,
        "initiate_checkout": 3,
        "purchases": 2,
        "dropoffs": {
          "impressions_to_link_clicks": 1.61,
          "link_clicks_to_landing": 19.9,
          "landing_to_cart": 13.3,
          "cart_to_checkout": 37.5,
          "cart_to_purchase": 25.0,
          "checkout_to_purchase": 66.7
        }
      }
    },
    {
      "id": "120243432146470161",
      "name": "TOF_SCALING_WELLNESS_CBO_230326",
      "status": "PAUSED",
      "objective": "OUTCOME_SALES",
      "reach": 0,
      "impressions": 0,
      "frequency": 0.0,
      "spend": 0.0,
      "link_clicks": 0,
      "ctr": 0.0,
      "cpm": 0.0,
      "cpc": 0.0,
      "landing_views": 0,
      "cost_per_landing_view": 0,
      "atc": 0,
      "cost_per_atc": 0,
      "initiate_checkout": 0,
      "cost_per_initiate_checkout": 0,
      "atc_abandon_rate": 0,
      "checkout_abandon_rate": 0,
      "purchases": 0,
      "revenue": 0.0,
      "roas": 0,
      "cac": 0,
      "funnel": {
        "reach": 0,
        "impressions": 0,
        "link_clicks": 0,
        "landing_views": 0,
        "add_to_cart": 0,
        "initiate_checkout": 0,
        "purchases": 0,
        "dropoffs": {
          "impressions_to_link_clicks": 0,
          "link_clicks_to_landing": 0,
          "landing_to_cart": 0,
          "cart_to_checkout": 0,
          "cart_to_purchase": 0,
          "checkout_to_purchase": 0
        }
      }
    },
    {
      "id": "120243156192820161",
      "name": "TOF_ABO_Regional_Campaign_170326",
      "status": "ACTIVE",
      "objective": "OUTCOME_SALES",
      "reach": 39741,
      "impressions": 51334,
      "frequency": 1.29,
      "spend": 6158.93,
      "link_clicks": 419,
      "ctr": 1.13,
      "cpm": 119.98,
      "cpc": 10.64,
      "landing_views": 331,
      "cost_per_landing_view": 18.61,
      "atc": 42,
      "cost_per_atc": 146.64,
      "initiate_checkout": 26,
      "cost_per_initiate_checkout": 236.88,
      "atc_abandon_rate": 76.2,
      "checkout_abandon_rate": 61.5,
      "purchases": 10,
      "revenue": 10275.2,
      "roas": 1.67,
      "cac": 615.89,
      "funnel": {
        "reach": 39741,
        "impressions": 51334,
        "link_clicks": 419,
        "landing_views": 331,
        "add_to_cart": 42,
        "initiate_checkout": 26,
        "purchases": 10,
        "dropoffs": {
          "impressions_to_link_clicks": 0.82,
          "link_clicks_to_landing": 79.0,
          "landing_to_cart": 12.7,
          "cart_to_checkout": 61.9,
          "cart_to_purchase": 23.8,
          "checkout_to_purchase": 38.5
        }
      }
    },
    {
      "id": "120243131623440161",
      "name": "TOF_ WhatsApp lead - B2B_170326",
      "status": "ACTIVE",
      "objective": "OUTCOME_LEADS",
      "reach": 222116,
      "impressions": 394294,
      "frequency": 1.78,
      "spend": 13894.62,
      "link_clicks": 2011,
      "ctr": 0.87,
      "cpm": 35.24,
      "cpc": 4.07,
      "landing_views": 13,
      "cost_per_landing_view": 1068.82,
      "atc": 2,
      "cost_per_atc": 6947.31,
      "initiate_checkout": 2,
      "cost_per_initiate_checkout": 6947.31,
      "atc_abandon_rate": 100.0,
      "checkout_abandon_rate": 100.0,
      "purchases": 0,
      "revenue": 0.0,
      "roas": 0,
      "cac": 0,
      "funnel": {
        "reach": 222116,
        "impressions": 394294,
        "link_clicks": 2011,
        "landing_views": 13,
        "add_to_cart": 2,
        "initiate_checkout": 2,
        "purchases": 0,
        "dropoffs": {
          "impressions_to_link_clicks": 0.51,
          "link_clicks_to_landing": 0.6,
          "landing_to_cart": 15.4,
          "cart_to_checkout": 100.0,
          "cart_to_purchase": 0.0,
          "checkout_to_purchase": 0.0
        }
      }
    },
    {
      "id": "120242935172170161",
      "name": "TOF_AD_CTWinners_140326",
      "status": "PAUSED",
      "objective": "OUTCOME_SALES",
      "reach": 0,
      "impressions": 0,
      "frequency": 0.0,
      "spend": 0.0,
      "link_clicks": 0,
      "ctr": 0.0,
      "cpm": 0.0,
      "cpc": 0.0,
      "landing_views": 0,
      "cost_per_landing_view": 0,
      "atc": 0,
      "cost_per_atc": 0,
      "initiate_checkout": 0,
      "cost_per_initiate_checkout": 0,
      "atc_abandon_rate": 0,
      "checkout_abandon_rate": 0,
      "purchases": 0,
      "revenue": 0.0,
      "roas": 0,
      "cac": 0,
      "funnel": {
        "reach": 0,
        "impressions": 0,
        "link_clicks": 0,
        "landing_views": 0,
        "add_to_cart": 0,
        "initiate_checkout": 0,
        "purchases": 0,
        "dropoffs": {
          "impressions_to_link_clicks": 0,
          "link_clicks_to_landing": 0,
          "landing_to_cart": 0,
          "cart_to_checkout": 0,
          "cart_to_purchase": 0,
          "checkout_to_purchase": 0
        }
      }
    },
    {
      "id": "120242929159510161",
      "name": "TOF_Jam&Sauce_ABO_140326",
      "status": "ACTIVE",
      "objective": "OUTCOME_SALES",
      "reach": 60945,
      "impressions": 88326,
      "frequency": 1.45,
      "spend": 20447.86,
      "link_clicks": 1404,
      "ctr": 2.12,
      "cpm": 231.5,
      "cpc": 10.93,
      "landing_views": 965,
      "cost_per_landing_view": 21.19,
      "atc": 143,
      "cost_per_atc": 142.99,
      "initiate_checkout": 113,
      "cost_per_initiate_checkout": 180.95,
      "atc_abandon_rate": 74.8,
      "checkout_abandon_rate": 68.1,
      "purchases": 36,
      "revenue": 32428.5,
      "roas": 1.59,
      "cac": 568.0,
      "funnel": {
        "reach": 60945,
        "impressions": 88326,
        "link_clicks": 1404,
        "landing_views": 965,
        "add_to_cart": 143,
        "initiate_checkout": 113,
        "purchases": 36,
        "dropoffs": {
          "impressions_to_link_clicks": 1.59,
          "link_clicks_to_landing": 68.7,
          "landing_to_cart": 14.8,
          "cart_to_checkout": 79.0,
          "cart_to_purchase": 25.2,
          "checkout_to_purchase": 31.9
        }
      }
    },
    {
      "id": "120242867608740161",
      "name": "TOF_WELLNESS_ABO_130326",
      "status": "ACTIVE",
      "objective": "OUTCOME_SALES",
      "reach": 72173,
      "impressions": 134462,
      "frequency": 1.86,
      "spend": 59238.41,
      "link_clicks": 2587,
      "ctr": 2.28,
      "cpm": 440.56,
      "cpc": 19.31,
      "landing_views": 1905,
      "cost_per_landing_view": 31.1,
      "atc": 304,
      "cost_per_atc": 194.86,
      "initiate_checkout": 252,
      "cost_per_initiate_checkout": 235.07,
      "atc_abandon_rate": 67.4,
      "checkout_abandon_rate": 60.7,
      "purchases": 99,
      "revenue": 80652.3,
      "roas": 1.36,
      "cac": 598.37,
      "funnel": {
        "reach": 72173,
        "impressions": 134462,
        "link_clicks": 2587,
        "landing_views": 1905,
        "add_to_cart": 304,
        "initiate_checkout": 252,
        "purchases": 99,
        "dropoffs": {
          "impressions_to_link_clicks": 1.92,
          "link_clicks_to_landing": 73.6,
          "landing_to_cart": 16.0,
          "cart_to_checkout": 82.9,
          "cart_to_purchase": 32.6,
          "checkout_to_purchase": 39.3
        }
      }
    },
    {
      "id": "120242865698210161",
      "name": "TOF_WELLNESS_ABO_130326",
      "status": "PAUSED",
      "objective": "OUTCOME_SALES",
      "reach": 0,
      "impressions": 0,
      "frequency": 0.0,
      "spend": 0.0,
      "link_clicks": 0,
      "ctr": 0.0,
      "cpm": 0.0,
      "cpc": 0.0,
      "landing_views": 0,
      "cost_per_landing_view": 0,
      "atc": 0,
      "cost_per_atc": 0,
      "initiate_checkout": 0,
      "cost_per_initiate_checkout": 0,
      "atc_abandon_rate": 0,
      "checkout_abandon_rate": 0,
      "purchases": 0,
      "revenue": 0.0,
      "roas": 0,
      "cac": 0,
      "funnel": {
        "reach": 0,
        "impressions": 0,
        "link_clicks": 0,
        "landing_views": 0,
        "add_to_cart": 0,
        "initiate_checkout": 0,
        "purchases": 0,
        "dropoffs": {
          "impressions_to_link_clicks": 0,
          "link_clicks_to_landing": 0,
          "landing_to_cart": 0,
          "cart_to_checkout": 0,
          "cart_to_purchase": 0,
          "checkout_to_purchase": 0
        }
      }
    },
    {
      "id": "120242067966070161",
      "name": "TOF | Brand Awareness",
      "status": "ACTIVE",
      "objective": "OUTCOME_AWARENESS",
      "reach": 1526412,
      "impressions": 1577087,
      "frequency": 1.03,
      "spend": 3274.13,
      "link_clicks": 42,
      "ctr": 0.07,
      "cpm": 2.08,
      "cpc": 3.03,
      "landing_views": 21,
      "cost_per_landing_view": 155.91,
      "atc": 0,
      "cost_per_atc": 0,
      "initiate_checkout": 0,
      "cost_per_initiate_checkout": 0,
      "atc_abandon_rate": 0,
      "checkout_abandon_rate": 0,
      "purchases": 0,
      "revenue": 0.0,
      "roas": 0,
      "cac": 0,
      "funnel": {
        "reach": 1526412,
        "impressions": 1577087,
        "link_clicks": 42,
        "landing_views": 21,
        "add_to_cart": 0,
        "initiate_checkout": 0,
        "purchases": 0,
        "dropoffs": {
          "impressions_to_link_clicks": 0.0,
          "link_clicks_to_landing": 50.0,
          "landing_to_cart": 0.0,
          "cart_to_checkout": 0,
          "cart_to_purchase": 0,
          "checkout_to_purchase": 0
        }
      }
    },
    {
      "id": "120239860888480161",
      "name": "TOF | WhatsApp lead - B2B | 16/1/2026",
      "status": "PAUSED",
      "objective": "OUTCOME_LEADS",
      "reach": 0,
      "impressions": 0,
      "frequency": 0.0,
      "spend": 0.0,
      "link_clicks": 0,
      "ctr": 0.0,
      "cpm": 0.0,
      "cpc": 0.0,
      "landing_views": 0,
      "cost_per_landing_view": 0,
      "atc": 0,
      "cost_per_atc": 0,
      "initiate_checkout": 0,
      "cost_per_initiate_checkout": 0,
      "atc_abandon_rate": 0,
      "checkout_abandon_rate": 0,
      "purchases": 0,
      "revenue": 0.0,
      "roas": 0,
      "cac": 0,
      "funnel": {
        "reach": 0,
        "impressions": 0,
        "link_clicks": 0,
        "landing_views": 0,
        "add_to_cart": 0,
        "initiate_checkout": 0,
        "purchases": 0,
        "dropoffs": {
          "impressions_to_link_clicks": 0,
          "link_clicks_to_landing": 0,
          "landing_to_cart": 0,
          "cart_to_checkout": 0,
          "cart_to_purchase": 0,
          "checkout_to_purchase": 0
        }
      }
    },
    {
      "id": "120239115875370161",
      "name": "CM | Nutrition Specific | 13/12/25",
      "status": "PAUSED",
      "objective": "OUTCOME_SALES",
      "reach": 0,
      "impressions": 0,
      "frequency": 0.0,
      "spend": 0.0,
      "link_clicks": 0,
      "ctr": 0.0,
      "cpm": 0.0,
      "cpc": 0.0,
      "landing_views": 0,
      "cost_per_landing_view": 0,
      "atc": 0,
      "cost_per_atc": 0,
      "initiate_checkout": 0,
      "cost_per_initiate_checkout": 0,
      "atc_abandon_rate": 0,
      "checkout_abandon_rate": 0,
      "purchases": 0,
      "revenue": 0.0,
      "roas": 0,
      "cac": 0,
      "funnel": {
        "reach": 0,
        "impressions": 0,
        "link_clicks": 0,
        "landing_views": 0,
        "add_to_cart": 0,
        "initiate_checkout": 0,
        "purchases": 0,
        "dropoffs": {
          "impressions_to_link_clicks": 0,
          "link_clicks_to_landing": 0,
          "landing_to_cart": 0,
          "cart_to_checkout": 0,
          "cart_to_purchase": 0,
          "checkout_to_purchase": 0
        }
      }
    },
    {
      "id": "120239112575060161",
      "name": "A+S | Creative test - Mixed Products | 1/4/2025",
      "status": "PAUSED",
      "objective": "OUTCOME_SALES",
      "reach": 0,
      "impressions": 0,
      "frequency": 0.0,
      "spend": 0.0,
      "link_clicks": 0,
      "ctr": 0.0,
      "cpm": 0.0,
      "cpc": 0.0,
      "landing_views": 0,
      "cost_per_landing_view": 0,
      "atc": 0,
      "cost_per_atc": 0,
      "initiate_checkout": 0,
      "cost_per_initiate_checkout": 0,
      "atc_abandon_rate": 0,
      "checkout_abandon_rate": 0,
      "purchases": 0,
      "revenue": 0.0,
      "roas": 0,
      "cac": 0,
      "funnel": {
        "reach": 0,
        "impressions": 0,
        "link_clicks": 0,
        "landing_views": 0,
        "add_to_cart": 0,
        "initiate_checkout": 0,
        "purchases": 0,
        "dropoffs": {
          "impressions_to_link_clicks": 0,
          "link_clicks_to_landing": 0,
          "landing_to_cart": 0,
          "cart_to_checkout": 0,
          "cart_to_purchase": 0,
          "checkout_to_purchase": 0
        }
      }
    },
    {
      "id": "120239047825250161",
      "name": "CM | Jamun Strips & Cubes | 06/08/25",
      "status": "ACTIVE",
      "objective": "OUTCOME_SALES",
      "reach": 144767,
      "impressions": 191255,
      "frequency": 1.32,
      "spend": 73788.9,
      "link_clicks": 3040,
      "ctr": 2.14,
      "cpm": 385.81,
      "cpc": 18.02,
      "landing_views": 2568,
      "cost_per_landing_view": 28.73,
      "atc": 441,
      "cost_per_atc": 167.32,
      "initiate_checkout": 351,
      "cost_per_initiate_checkout": 210.22,
      "atc_abandon_rate": 69.2,
      "checkout_abandon_rate": 61.3,
      "purchases": 136,
      "revenue": 111709.98,
      "roas": 1.51,
      "cac": 542.57,
      "funnel": {
        "reach": 144767,
        "impressions": 191255,
        "link_clicks": 3040,
        "landing_views": 2568,
        "add_to_cart": 441,
        "initiate_checkout": 351,
        "purchases": 136,
        "dropoffs": {
          "impressions_to_link_clicks": 1.59,
          "link_clicks_to_landing": 84.5,
          "landing_to_cart": 17.2,
          "cart_to_checkout": 79.6,
          "cart_to_purchase": 30.8,
          "checkout_to_purchase": 38.7
        }
      }
    },
    {
      "id": "120239047503140161",
      "name": "TOF | New Video Creatives Test | 28/05/25",
      "status": "ACTIVE",
      "objective": "OUTCOME_SALES",
      "reach": 90797,
      "impressions": 208066,
      "frequency": 2.29,
      "spend": 73681.21,
      "link_clicks": 3281,
      "ctr": 1.89,
      "cpm": 354.12,
      "cpc": 18.71,
      "landing_views": 2559,
      "cost_per_landing_view": 28.79,
      "atc": 310,
      "cost_per_atc": 237.68,
      "initiate_checkout": 236,
      "cost_per_initiate_checkout": 312.21,
      "atc_abandon_rate": 70.3,
      "checkout_abandon_rate": 61.0,
      "purchases": 92,
      "revenue": 98559.03,
      "roas": 1.34,
      "cac": 800.88,
      "funnel": {
        "reach": 90797,
        "impressions": 208066,
        "link_clicks": 3281,
        "landing_views": 2559,
        "add_to_cart": 310,
        "initiate_checkout": 236,
        "purchases": 92,
        "dropoffs": {
          "impressions_to_link_clicks": 1.58,
          "link_clicks_to_landing": 78.0,
          "landing_to_cart": 12.1,
          "cart_to_checkout": 76.1,
          "cart_to_purchase": 29.7,
          "checkout_to_purchase": 39.0
        }
      }
    },
    {
      "id": "120239046978990161",
      "name": "TOF | ROAS Cap - Performers | 10/9/2025",
      "status": "PAUSED",
      "objective": "OUTCOME_SALES",
      "reach": 0,
      "impressions": 0,
      "frequency": 0.0,
      "spend": 0.0,
      "link_clicks": 0,
      "ctr": 0.0,
      "cpm": 0.0,
      "cpc": 0.0,
      "landing_views": 0,
      "cost_per_landing_view": 0,
      "atc": 0,
      "cost_per_atc": 0,
      "initiate_checkout": 0,
      "cost_per_initiate_checkout": 0,
      "atc_abandon_rate": 0,
      "checkout_abandon_rate": 0,
      "purchases": 0,
      "revenue": 0.0,
      "roas": 0,
      "cac": 0,
      "funnel": {
        "reach": 0,
        "impressions": 0,
        "link_clicks": 0,
        "landing_views": 0,
        "add_to_cart": 0,
        "initiate_checkout": 0,
        "purchases": 0,
        "dropoffs": {
          "impressions_to_link_clicks": 0,
          "link_clicks_to_landing": 0,
          "landing_to_cart": 0,
          "cart_to_checkout": 0,
          "cart_to_purchase": 0,
          "checkout_to_purchase": 0
        }
      }
    },
    {
      "id": "120239044894930161",
      "name": "CM | Frozen Specific | 05/12/2025",
      "status": "ACTIVE",
      "objective": "OUTCOME_SALES",
      "reach": 695741,
      "impressions": 1141519,
      "frequency": 1.64,
      "spend": 193837.47,
      "link_clicks": 12596,
      "ctr": 1.46,
      "cpm": 169.81,
      "cpc": 11.62,
      "landing_views": 10745,
      "cost_per_landing_view": 18.04,
      "atc": 1257,
      "cost_per_atc": 154.21,
      "initiate_checkout": 1039,
      "cost_per_initiate_checkout": 186.56,
      "atc_abandon_rate": 67.7,
      "checkout_abandon_rate": 60.9,
      "purchases": 406,
      "revenue": 474860.44,
      "roas": 2.45,
      "cac": 477.43,
      "funnel": {
        "reach": 695741,
        "impressions": 1141519,
        "link_clicks": 12596,
        "landing_views": 10745,
        "add_to_cart": 1257,
        "initiate_checkout": 1039,
        "purchases": 406,
        "dropoffs": {
          "impressions_to_link_clicks": 1.1,
          "link_clicks_to_landing": 85.3,
          "landing_to_cart": 11.7,
          "cart_to_checkout": 82.7,
          "cart_to_purchase": 32.3,
          "checkout_to_purchase": 39.1
        }
      }
    },
    {
      "id": "120239044078200161",
      "name": "TOF | Catalog sales - All products | 21/11/2025",
      "status": "ACTIVE",
      "objective": "OUTCOME_SALES",
      "reach": 147401,
      "impressions": 322229,
      "frequency": 2.19,
      "spend": 86553.55,
      "link_clicks": 3876,
      "ctr": 1.44,
      "cpm": 268.61,
      "cpc": 18.71,
      "landing_views": 2800,
      "cost_per_landing_view": 30.91,
      "atc": 347,
      "cost_per_atc": 249.43,
      "initiate_checkout": 268,
      "cost_per_initiate_checkout": 322.96,
      "atc_abandon_rate": 63.4,
      "checkout_abandon_rate": 52.6,
      "purchases": 127,
      "revenue": 127282.64,
      "roas": 1.47,
      "cac": 681.52,
      "funnel": {
        "reach": 147401,
        "impressions": 322229,
        "link_clicks": 3876,
        "landing_views": 2800,
        "add_to_cart": 347,
        "initiate_checkout": 268,
        "purchases": 127,
        "dropoffs": {
          "impressions_to_link_clicks": 1.2,
          "link_clicks_to_landing": 72.2,
          "landing_to_cart": 12.4,
          "cart_to_checkout": 77.2,
          "cart_to_purchase": 36.6,
          "checkout_to_purchase": 47.4
        }
      }
    },
    {
      "id": "120239042395530161",
      "name": "CM | Brand Specific | 04/12/25",
      "status": "ACTIVE",
      "objective": "OUTCOME_SALES",
      "reach": 105100,
      "impressions": 169799,
      "frequency": 1.62,
      "spend": 54693.84,
      "link_clicks": 2958,
      "ctr": 2.22,
      "cpm": 322.11,
      "cpc": 14.52,
      "landing_views": 2180,
      "cost_per_landing_view": 25.09,
      "atc": 204,
      "cost_per_atc": 268.11,
      "initiate_checkout": 174,
      "cost_per_initiate_checkout": 314.33,
      "atc_abandon_rate": 61.3,
      "checkout_abandon_rate": 54.6,
      "purchases": 79,
      "revenue": 87180.2,
      "roas": 1.59,
      "cac": 692.33,
      "funnel": {
        "reach": 105100,
        "impressions": 169799,
        "link_clicks": 2958,
        "landing_views": 2180,
        "add_to_cart": 204,
        "initiate_checkout": 174,
        "purchases": 79,
        "dropoffs": {
          "impressions_to_link_clicks": 1.74,
          "link_clicks_to_landing": 73.7,
          "landing_to_cart": 9.4,
          "cart_to_checkout": 85.3,
          "cart_to_purchase": 38.7,
          "checkout_to_purchase": 45.4
        }
      }
    },
    {
      "id": "120223421188820161",
      "name": "A+S | Jamun Strip - Pilot test | 24/4/2025 Campaign",
      "status": "PAUSED",
      "objective": "OUTCOME_SALES",
      "reach": 0,
      "impressions": 0,
      "frequency": 0.0,
      "spend": 0.0,
      "link_clicks": 0,
      "ctr": 0.0,
      "cpm": 0.0,
      "cpc": 0.0,
      "landing_views": 0,
      "cost_per_landing_view": 0,
      "atc": 0,
      "cost_per_atc": 0,
      "initiate_checkout": 0,
      "cost_per_initiate_checkout": 0,
      "atc_abandon_rate": 0,
      "checkout_abandon_rate": 0,
      "purchases": 0,
      "revenue": 0.0,
      "roas": 0,
      "cac": 0,
      "funnel": {
        "reach": 0,
        "impressions": 0,
        "link_clicks": 0,
        "landing_views": 0,
        "add_to_cart": 0,
        "initiate_checkout": 0,
        "purchases": 0,
        "dropoffs": {
          "impressions_to_link_clicks": 0,
          "link_clicks_to_landing": 0,
          "landing_to_cart": 0,
          "cart_to_checkout": 0,
          "cart_to_purchase": 0,
          "checkout_to_purchase": 0
        }
      }
    }
  ],
  "adsets": [
    {
      "id": "120244946428710161",
      "name": "Frozen Shot -  Engagement | All India | 170626",
      "status": "ACTIVE",
      "daily_budget": 0.0,
      "spend": 202.95,
      "impressions": 110462,
      "frequency": 1.05,
      "link_clicks": 41,
      "ctr": 0.06,
      "cpm": 1.84,
      "cpc": 2.98,
      "landing_views": 21,
      "cost_per_landing_view": 9.66,
      "atc": 0,
      "cost_per_atc": 0,
      "initiate_checkout": 0,
      "cost_per_initiate_checkout": 0,
      "atc_abandon_rate": 0,
      "checkout_abandon_rate": 0,
      "purchases": 0,
      "cac": 0,
      "age": "18\u201365",
      "gender": "All"
    },
    {
      "id": "120244785902900161",
      "name": "All India | Frozen Shots | VDCT | 140426",
      "status": "ACTIVE",
      "daily_budget": 1000.0,
      "spend": 2472.34,
      "impressions": 10606,
      "frequency": 1.3,
      "link_clicks": 73,
      "ctr": 1.07,
      "cpm": 233.11,
      "cpc": 21.88,
      "landing_views": 55,
      "cost_per_landing_view": 44.95,
      "atc": 8,
      "cost_per_atc": 309.04,
      "initiate_checkout": 6,
      "cost_per_initiate_checkout": 412.06,
      "atc_abandon_rate": 75.0,
      "checkout_abandon_rate": 66.7,
      "purchases": 2,
      "cac": 1236.17,
      "age": "18\u201365",
      "gender": "All"
    },
    {
      "id": "120244731059050161",
      "name": "All India | Frozen Shots | VDCT | 130426",
      "status": "ACTIVE",
      "daily_budget": 2000.0,
      "spend": 7340.1,
      "impressions": 34423,
      "frequency": 1.3,
      "link_clicks": 270,
      "ctr": 1.12,
      "cpm": 213.23,
      "cpc": 19.11,
      "landing_views": 235,
      "cost_per_landing_view": 31.23,
      "atc": 44,
      "cost_per_atc": 166.82,
      "initiate_checkout": 37,
      "cost_per_initiate_checkout": 198.38,
      "atc_abandon_rate": 75.0,
      "checkout_abandon_rate": 70.3,
      "purchases": 11,
      "cac": 667.28,
      "age": "18\u201365",
      "gender": "All"
    },
    {
      "id": "120244444255210161",
      "name": "All India | Frozen Shots | IMGCT | 080426",
      "status": "ACTIVE",
      "daily_budget": 1000.0,
      "spend": 6125.95,
      "impressions": 49880,
      "frequency": 1.25,
      "link_clicks": 574,
      "ctr": 1.67,
      "cpm": 122.81,
      "cpc": 7.37,
      "landing_views": 475,
      "cost_per_landing_view": 12.9,
      "atc": 64,
      "cost_per_atc": 95.72,
      "initiate_checkout": 61,
      "cost_per_initiate_checkout": 100.43,
      "atc_abandon_rate": 70.3,
      "checkout_abandon_rate": 68.9,
      "purchases": 19,
      "cac": 322.42,
      "age": "18\u201365",
      "gender": "All"
    },
    {
      "id": "120244302681690161",
      "name": "Top Cities",
      "status": "ACTIVE",
      "daily_budget": 0.0,
      "spend": 216343.52,
      "impressions": 2226871,
      "frequency": 1.53,
      "link_clicks": 19717,
      "ctr": 1.16,
      "cpm": 97.15,
      "cpc": 8.34,
      "landing_views": 15317,
      "cost_per_landing_view": 14.12,
      "atc": 1466,
      "cost_per_atc": 147.57,
      "initiate_checkout": 1212,
      "cost_per_initiate_checkout": 178.5,
      "atc_abandon_rate": 68.8,
      "checkout_abandon_rate": 62.3,
      "purchases": 457,
      "cac": 473.4,
      "age": "18\u201365",
      "gender": "All"
    },
    {
      "id": "120244260633630161",
      "name": "Mumbai | Frozen Shots | VDCT | 050426",
      "status": "ACTIVE",
      "daily_budget": 3000.0,
      "spend": 17263.47,
      "impressions": 82143,
      "frequency": 1.39,
      "link_clicks": 1055,
      "ctr": 1.62,
      "cpm": 210.16,
      "cpc": 12.96,
      "landing_views": 955,
      "cost_per_landing_view": 18.08,
      "atc": 120,
      "cost_per_atc": 143.86,
      "initiate_checkout": 100,
      "cost_per_initiate_checkout": 172.63,
      "atc_abandon_rate": 67.5,
      "checkout_abandon_rate": 61.0,
      "purchases": 39,
      "cac": 442.65,
      "age": "18\u201365",
      "gender": "All"
    },
    {
      "id": "120244260254750161",
      "name": "All India | Frozen Shots | VDCT | 050426",
      "status": "ACTIVE",
      "daily_budget": 2000.0,
      "spend": 11901.83,
      "impressions": 50910,
      "frequency": 1.49,
      "link_clicks": 359,
      "ctr": 1.03,
      "cpm": 233.78,
      "cpc": 22.71,
      "landing_views": 311,
      "cost_per_landing_view": 38.27,
      "atc": 85,
      "cost_per_atc": 140.02,
      "initiate_checkout": 66,
      "cost_per_initiate_checkout": 180.33,
      "atc_abandon_rate": 74.1,
      "checkout_abandon_rate": 66.7,
      "purchases": 22,
      "cac": 540.99,
      "age": "18\u201365",
      "gender": "All"
    },
    {
      "id": "120244227206120161",
      "name": "All India | Frozen Shots | VDCT | 040426",
      "status": "ACTIVE",
      "daily_budget": 5500.0,
      "spend": 39856.73,
      "impressions": 278637,
      "frequency": 1.24,
      "link_clicks": 2789,
      "ctr": 1.34,
      "cpm": 143.04,
      "cpc": 10.67,
      "landing_views": 2237,
      "cost_per_landing_view": 17.82,
      "atc": 245,
      "cost_per_atc": 162.68,
      "initiate_checkout": 204,
      "cost_per_initiate_checkout": 195.38,
      "atc_abandon_rate": 72.2,
      "checkout_abandon_rate": 66.7,
      "purchases": 68,
      "cac": 586.13,
      "age": "18\u201365",
      "gender": "All"
    },
    {
      "id": "120244145495790161",
      "name": "All India | Frozen Shots | VDCT | 030426",
      "status": "ACTIVE",
      "daily_budget": 10000.0,
      "spend": 68380.59,
      "impressions": 381122,
      "frequency": 1.36,
      "link_clicks": 4748,
      "ctr": 1.61,
      "cpm": 179.42,
      "cpc": 11.11,
      "landing_views": 4091,
      "cost_per_landing_view": 16.71,
      "atc": 447,
      "cost_per_atc": 152.98,
      "initiate_checkout": 369,
      "cost_per_initiate_checkout": 185.31,
      "atc_abandon_rate": 64.7,
      "checkout_abandon_rate": 57.2,
      "purchases": 158,
      "cac": 432.79,
      "age": "18\u201365",
      "gender": "All"
    },
    {
      "id": "120244073473760161",
      "name": "All India | Frozen Shots | VDCT | 020426",
      "status": "ACTIVE",
      "daily_budget": 5500.0,
      "spend": 40496.46,
      "impressions": 253798,
      "frequency": 1.27,
      "link_clicks": 2728,
      "ctr": 1.42,
      "cpm": 159.56,
      "cpc": 11.2,
      "landing_views": 2386,
      "cost_per_landing_view": 16.97,
      "atc": 243,
      "cost_per_atc": 166.65,
      "initiate_checkout": 195,
      "cost_per_initiate_checkout": 207.67,
      "atc_abandon_rate": 64.2,
      "checkout_abandon_rate": 55.4,
      "purchases": 87,
      "cac": 465.48,
      "age": "18\u201365",
      "gender": "All"
    },
    {
      "id": "120243993730690161",
      "name": "Amazon LP | Advantage+",
      "status": "ACTIVE",
      "daily_budget": 0.0,
      "spend": 2633.87,
      "impressions": 15158,
      "frequency": 1.35,
      "link_clicks": 211,
      "ctr": 1.38,
      "cpm": 173.76,
      "cpc": 12.6,
      "landing_views": 50,
      "cost_per_landing_view": 52.68,
      "atc": 5,
      "cost_per_atc": 526.77,
      "initiate_checkout": 1,
      "cost_per_initiate_checkout": 2633.87,
      "atc_abandon_rate": 60.0,
      "checkout_abandon_rate": -100.0,
      "purchases": 2,
      "cac": 1316.93,
      "age": "18\u201365",
      "gender": "All"
    },
    {
      "id": "120243993730680161",
      "name": "Amazon LP | Advantage+ | Strips video",
      "status": "ACTIVE",
      "daily_budget": 0.0,
      "spend": 705.82,
      "impressions": 3496,
      "frequency": 1.2,
      "link_clicks": 90,
      "ctr": 2.4,
      "cpm": 201.89,
      "cpc": 8.4,
      "landing_views": 10,
      "cost_per_landing_view": 70.58,
      "atc": 3,
      "cost_per_atc": 235.27,
      "initiate_checkout": 2,
      "cost_per_initiate_checkout": 352.91,
      "atc_abandon_rate": 100.0,
      "checkout_abandon_rate": 100.0,
      "purchases": 0,
      "cac": 0,
      "age": "18\u201365",
      "gender": "All"
    },
    {
      "id": "120243754651990161",
      "name": "Ahmedabad | UGC | Batch 05",
      "status": "PAUSED",
      "daily_budget": 500.0,
      "spend": 0.0,
      "impressions": 0,
      "frequency": 0.0,
      "link_clicks": 0,
      "ctr": 0.0,
      "cpm": 0.0,
      "cpc": 0.0,
      "landing_views": 0,
      "cost_per_landing_view": 0,
      "atc": 0,
      "cost_per_atc": 0,
      "initiate_checkout": 0,
      "cost_per_initiate_checkout": 0,
      "atc_abandon_rate": 0,
      "checkout_abandon_rate": 0,
      "purchases": 0,
      "cac": 0,
      "age": "18\u201365",
      "gender": "All"
    },
    {
      "id": "120243750635620161",
      "name": "Bangalore+Mumbai | UGC | Batch 05",
      "status": "PAUSED",
      "daily_budget": 800.0,
      "spend": 0.0,
      "impressions": 0,
      "frequency": 0.0,
      "link_clicks": 0,
      "ctr": 0.0,
      "cpm": 0.0,
      "cpc": 0.0,
      "landing_views": 0,
      "cost_per_landing_view": 0,
      "atc": 0,
      "cost_per_atc": 0,
      "initiate_checkout": 0,
      "cost_per_initiate_checkout": 0,
      "atc_abandon_rate": 0,
      "checkout_abandon_rate": 0,
      "purchases": 0,
      "cac": 0,
      "age": "18\u201365",
      "gender": "All"
    },
    {
      "id": "120243630880490161",
      "name": "Ahmedabad | UGC | Batch 3 - Only AHM",
      "status": "PAUSED",
      "daily_budget": 2000.0,
      "spend": 0.0,
      "impressions": 0,
      "frequency": 0.0,
      "link_clicks": 0,
      "ctr": 0.0,
      "cpm": 0.0,
      "cpc": 0.0,
      "landing_views": 0,
      "cost_per_landing_view": 0,
      "atc": 0,
      "cost_per_atc": 0,
      "initiate_checkout": 0,
      "cost_per_initiate_checkout": 0,
      "atc_abandon_rate": 0,
      "checkout_abandon_rate": 0,
      "purchases": 0,
      "cac": 0,
      "age": "18\u201365",
      "gender": "All"
    },
    {
      "id": "120243563203840161",
      "name": "Open AUD | Sugar Combo | 25/3/2026",
      "status": "ACTIVE",
      "daily_budget": 800.0,
      "spend": 6756.12,
      "impressions": 19613,
      "frequency": 1.45,
      "link_clicks": 193,
      "ctr": 1.42,
      "cpm": 344.47,
      "cpc": 24.22,
      "landing_views": 175,
      "cost_per_landing_view": 38.61,
      "atc": 27,
      "cost_per_atc": 250.23,
      "initiate_checkout": 28,
      "cost_per_initiate_checkout": 241.29,
      "atc_abandon_rate": 70.4,
      "checkout_abandon_rate": 71.4,
      "purchases": 8,
      "cac": 844.51,
      "age": "18\u201365",
      "gender": "All"
    },
    {
      "id": "120243562429440161",
      "name": "Open AUD | Mascot Batch | 25/3/2026",
      "status": "PAUSED",
      "daily_budget": 800.0,
      "spend": 0.0,
      "impressions": 0,
      "frequency": 0.0,
      "link_clicks": 0,
      "ctr": 0.0,
      "cpm": 0.0,
      "cpc": 0.0,
      "landing_views": 0,
      "cost_per_landing_view": 0,
      "atc": 0,
      "cost_per_atc": 0,
      "initiate_checkout": 0,
      "cost_per_initiate_checkout": 0,
      "atc_abandon_rate": 0,
      "checkout_abandon_rate": 0,
      "purchases": 0,
      "cac": 0,
      "age": "18\u201365",
      "gender": "All"
    },
    {
      "id": "120243553089990161",
      "name": "Open AUD | Static CT | Holo-WR | 250326",
      "status": "ACTIVE",
      "daily_budget": 1000.0,
      "spend": 8150.16,
      "impressions": 25377,
      "frequency": 1.49,
      "link_clicks": 340,
      "ctr": 2.1,
      "cpm": 321.16,
      "cpc": 15.26,
      "landing_views": 258,
      "cost_per_landing_view": 31.59,
      "atc": 43,
      "cost_per_atc": 189.54,
      "initiate_checkout": 31,
      "cost_per_initiate_checkout": 262.91,
      "atc_abandon_rate": 72.1,
      "checkout_abandon_rate": 61.3,
      "purchases": 12,
      "cac": 679.18,
      "age": "18\u201365",
      "gender": "All"
    },
    {
      "id": "120243432146500161",
      "name": "TV_WEL_KNJ+VINEGAR_WINNERCT_25-65+_OpenAUD",
      "status": "ACTIVE",
      "daily_budget": 0.0,
      "spend": 0.0,
      "impressions": 0,
      "frequency": 0.0,
      "link_clicks": 0,
      "ctr": 0.0,
      "cpm": 0.0,
      "cpc": 0.0,
      "landing_views": 0,
      "cost_per_landing_view": 0,
      "atc": 0,
      "cost_per_atc": 0,
      "initiate_checkout": 0,
      "cost_per_initiate_checkout": 0,
      "atc_abandon_rate": 0,
      "checkout_abandon_rate": 0,
      "purchases": 0,
      "cac": 0,
      "age": "18\u201365",
      "gender": "All"
    },
    {
      "id": "120243187617510161",
      "name": "TV-NUT-VID02-IG",
      "status": "PAUSED",
      "daily_budget": 1500.0,
      "spend": 0.0,
      "impressions": 0,
      "frequency": 0.0,
      "link_clicks": 0,
      "ctr": 0.0,
      "cpm": 0.0,
      "cpc": 0.0,
      "landing_views": 0,
      "cost_per_landing_view": 0,
      "atc": 0,
      "cost_per_atc": 0,
      "initiate_checkout": 0,
      "cost_per_initiate_checkout": 0,
      "atc_abandon_rate": 0,
      "checkout_abandon_rate": 0,
      "purchases": 0,
      "cac": 0,
      "age": "18\u201365",
      "gender": "All"
    }
  ],
  "ads": [
    {
      "id": "120244948556650161",
      "name": "Frozen Shot - 170426",
      "status": "ACTIVE",
      "adset": "120244946428710161",
      "spend": 202.95,
      "impressions": 110462,
      "frequency": 1.05,
      "link_clicks": 41,
      "ctr": 0.06,
      "cpm": 1.84,
      "cpc": 2.98,
      "landing_views": 21,
      "cost_per_landing_view": 9.66,
      "atc": 0,
      "cost_per_atc": 0,
      "initiate_checkout": 0,
      "cost_per_initiate_checkout": 0,
      "purchases": 0,
      "cac": 0,
      "revenue": 0.0,
      "roas": 0.0,
      "hook_rate": 5.75,
      "thumb_stop_rate": 0.04,
      "video_views_3s": 6356
    },
    {
      "id": "120244785902890161",
      "name": "Frozen April'26 01",
      "status": "ACTIVE",
      "adset": "120244785902900161",
      "spend": 2472.34,
      "impressions": 10606,
      "frequency": 1.3,
      "link_clicks": 73,
      "ctr": 1.07,
      "cpm": 233.11,
      "cpc": 21.88,
      "landing_views": 55,
      "cost_per_landing_view": 44.95,
      "atc": 8,
      "cost_per_atc": 309.04,
      "initiate_checkout": 6,
      "cost_per_initiate_checkout": 412.06,
      "purchases": 2,
      "cac": 1236.17,
      "revenue": 2944.2,
      "roas": 1.19,
      "hook_rate": 15.88,
      "thumb_stop_rate": 0.69,
      "video_views_3s": 1684
    },
    {
      "id": "120244731059060161",
      "name": "Frozen April'26 01",
      "status": "ACTIVE",
      "adset": "120244731059050161",
      "spend": 7340.1,
      "impressions": 34423,
      "frequency": 1.3,
      "link_clicks": 270,
      "ctr": 1.12,
      "cpm": 213.23,
      "cpc": 19.11,
      "landing_views": 235,
      "cost_per_landing_view": 31.23,
      "atc": 44,
      "cost_per_atc": 166.82,
      "initiate_checkout": 37,
      "cost_per_initiate_checkout": 198.38,
      "purchases": 11,
      "cac": 667.28,
      "revenue": 11233.2,
      "roas": 1.53,
      "hook_rate": 17.85,
      "thumb_stop_rate": 0.78,
      "video_views_3s": 6145
    },
    {
      "id": "120244445613020161",
      "name": "TV_FRO_IMG05",
      "status": "ACTIVE",
      "adset": "120244444255210161",
      "spend": 9.59,
      "impressions": 87,
      "frequency": 1.14,
      "link_clicks": 0,
      "ctr": 0.0,
      "cpm": 110.23,
      "cpc": 0.0,
      "landing_views": 0,
      "cost_per_landing_view": 0,
      "atc": 0,
      "cost_per_atc": 0,
      "initiate_checkout": 1,
      "cost_per_initiate_checkout": 9.59,
      "purchases": 0,
      "cac": 0,
      "revenue": 0.0,
      "roas": 0.0,
      "hook_rate": 0.0,
      "thumb_stop_rate": 0.0,
      "video_views_3s": 0
    },
    {
      "id": "120244444255190161",
      "name": "TV_FRO_IMG01",
      "status": "ACTIVE",
      "adset": "120244444255210161",
      "spend": 28.21,
      "impressions": 145,
      "frequency": 1.03,
      "link_clicks": 1,
      "ctr": 0.69,
      "cpm": 194.55,
      "cpc": 28.21,
      "landing_views": 1,
      "cost_per_landing_view": 28.21,
      "atc": 0,
      "cost_per_atc": 0,
      "initiate_checkout": 0,
      "cost_per_initiate_checkout": 0,
      "purchases": 0,
      "cac": 0,
      "revenue": 0.0,
      "roas": 0.0,
      "hook_rate": 0.0,
      "thumb_stop_rate": 0.69,
      "video_views_3s": 0
    },
    {
      "id": "120244444962210161",
      "name": "TV_FRO_IMG02",
      "status": "ACTIVE",
      "adset": "120244444255210161",
      "spend": 144.13,
      "impressions": 802,
      "frequency": 1.07,
      "link_clicks": 8,
      "ctr": 1.5,
      "cpm": 179.71,
      "cpc": 12.01,
      "landing_views": 8,
      "cost_per_landing_view": 18.02,
      "atc": 2,
      "cost_per_atc": 72.06,
      "initiate_checkout": 2,
      "cost_per_initiate_checkout": 72.06,
      "purchases": 1,
      "cac": 144.13,
      "revenue": 1894.0,
      "roas": 13.14,
      "hook_rate": 0.0,
      "thumb_stop_rate": 1.0,
      "video_views_3s": 0
    },
    {
      "id": "120244445236860161",
      "name": "TV_FRO_IMG03",
      "status": "ACTIVE",
      "adset": "120244444255210161",
      "spend": 5389.34,
      "impressions": 46193,
      "frequency": 1.25,
      "link_clicks": 541,
      "ctr": 1.71,
      "cpm": 116.67,
      "cpc": 6.84,
      "landing_views": 448,
      "cost_per_landing_view": 12.03,
      "atc": 61,
      "cost_per_atc": 88.35,
      "initiate_checkout": 56,
      "cost_per_initiate_checkout": 96.24,
      "purchases": 17,
      "cac": 317.02,
      "revenue": 20594.4,
      "roas": 3.82,
      "hook_rate": 0.0,
      "thumb_stop_rate": 1.17,
      "video_views_3s": 0
    },
    {
      "id": "120244445408940161",
      "name": "TV_FRO_IMG04",
      "status": "ACTIVE",
      "adset": "120244444255210161",
      "spend": 554.68,
      "impressions": 2653,
      "frequency": 1.1,
      "link_clicks": 24,
      "ctr": 1.13,
      "cpm": 209.08,
      "cpc": 18.49,
      "landing_views": 18,
      "cost_per_landing_view": 30.82,
      "atc": 1,
      "cost_per_atc": 554.68,
      "initiate_checkout": 2,
      "cost_per_initiate_checkout": 277.34,
      "purchases": 1,
      "cac": 554.68,
      "revenue": 1428.0,
      "roas": 2.57,
      "hook_rate": 0.0,
      "thumb_stop_rate": 0.9,
      "video_views_3s": 0
    },
    {
      "id": "120244330098160161",
      "name": "Test - TV_VD3_LP",
      "status": "PAUSED",
      "adset": "120242937632690161",
      "spend": 0.0,
      "impressions": 0,
      "frequency": 0.0,
      "link_clicks": 0,
      "ctr": 0.0,
      "cpm": 0.0,
      "cpc": 0.0,
      "landing_views": 0,
      "cost_per_landing_view": 0,
      "atc": 0,
      "cost_per_atc": 0,
      "initiate_checkout": 0,
      "cost_per_initiate_checkout": 0,
      "purchases": 0,
      "cac": 0,
      "revenue": 0.0,
      "roas": 0,
      "hook_rate": 0,
      "thumb_stop_rate": 0,
      "video_views_3s": 0
    },
    {
      "id": "120244330098150161",
      "name": "Test - TV_VD3",
      "status": "PAUSED",
      "adset": "120242937632690161",
      "spend": 0.0,
      "impressions": 0,
      "frequency": 0.0,
      "link_clicks": 0,
      "ctr": 0.0,
      "cpm": 0.0,
      "cpc": 0.0,
      "landing_views": 0,
      "cost_per_landing_view": 0,
      "atc": 0,
      "cost_per_atc": 0,
      "initiate_checkout": 0,
      "cost_per_initiate_checkout": 0,
      "purchases": 0,
      "cac": 0,
      "revenue": 0.0,
      "roas": 0,
      "hook_rate": 0,
      "thumb_stop_rate": 0,
      "video_views_3s": 0
    },
    {
      "id": "120242933575330161",
      "name": "TV_J+S_VD1",
      "status": "PAUSED",
      "adset": "120242929159460161",
      "spend": 0.0,
      "impressions": 0,
      "frequency": 0.0,
      "link_clicks": 0,
      "ctr": 0.0,
      "cpm": 0.0,
      "cpc": 0.0,
      "landing_views": 0,
      "cost_per_landing_view": 0,
      "atc": 0,
      "cost_per_atc": 0,
      "initiate_checkout": 0,
      "cost_per_initiate_checkout": 0,
      "purchases": 0,
      "cac": 0,
      "revenue": 0.0,
      "roas": 0,
      "hook_rate": 0,
      "thumb_stop_rate": 0,
      "video_views_3s": 0
    },
    {
      "id": "120239047581100161",
      "name": "Image 4 - Cubes",
      "status": "PAUSED",
      "adset": "120239047503150161",
      "spend": 0.0,
      "impressions": 0,
      "frequency": 0.0,
      "link_clicks": 0,
      "ctr": 0.0,
      "cpm": 0.0,
      "cpc": 0.0,
      "landing_views": 0,
      "cost_per_landing_view": 0,
      "atc": 0,
      "cost_per_atc": 0,
      "initiate_checkout": 0,
      "cost_per_initiate_checkout": 0,
      "purchases": 0,
      "cac": 0,
      "revenue": 0.0,
      "roas": 0,
      "hook_rate": 0,
      "thumb_stop_rate": 0,
      "video_views_3s": 0
    },
    {
      "id": "120244302773820161",
      "name": "Frozen 02 - Copy",
      "status": "ACTIVE",
      "adset": "120244302681690161",
      "spend": 7.3,
      "impressions": 18,
      "frequency": 1.06,
      "link_clicks": 0,
      "ctr": 0.0,
      "cpm": 405.56,
      "cpc": 0.0,
      "landing_views": 0,
      "cost_per_landing_view": 0,
      "atc": 0,
      "cost_per_atc": 0,
      "initiate_checkout": 0,
      "cost_per_initiate_checkout": 0,
      "purchases": 0,
      "cac": 0,
      "revenue": 0.0,
      "roas": 0.0,
      "hook_rate": 11.11,
      "thumb_stop_rate": 0.0,
      "video_views_3s": 2
    },
    {
      "id": "120244302773800161",
      "name": "TV_FRO_VID04 - Copy",
      "status": "ACTIVE",
      "adset": "120244302681690161",
      "spend": 153334.59,
      "impressions": 1821915,
      "frequency": 1.39,
      "link_clicks": 15521,
      "ctr": 1.11,
      "cpm": 84.16,
      "cpc": 7.55,
      "landing_views": 11888,
      "cost_per_landing_view": 12.9,
      "atc": 1073,
      "cost_per_atc": 142.9,
      "initiate_checkout": 910,
      "cost_per_initiate_checkout": 168.5,
      "purchases": 327,
      "cac": 468.91,
      "revenue": 367773.31,
      "roas": 2.4,
      "hook_rate": 21.53,
      "thumb_stop_rate": 0.85,
      "video_views_3s": 392312
    },
    {
      "id": "120244302773850161",
      "name": "Frozen 03 - Copy",
      "status": "ACTIVE",
      "adset": "120244302681690161",
      "spend": 342.42,
      "impressions": 1146,
      "frequency": 1.23,
      "link_clicks": 7,
      "ctr": 1.05,
      "cpm": 298.8,
      "cpc": 28.54,
      "landing_views": 7,
      "cost_per_landing_view": 48.92,
      "atc": 1,
      "cost_per_atc": 342.42,
      "initiate_checkout": 1,
      "cost_per_initiate_checkout": 342.42,
      "purchases": 1,
      "cac": 342.42,
      "revenue": 1030.0,
      "roas": 3.01,
      "hook_rate": 17.36,
      "thumb_stop_rate": 0.61,
      "video_views_3s": 199
    },
    {
      "id": "120244302773840161",
      "name": "TV_FRO_VID01 - Copy",
      "status": "ACTIVE",
      "adset": "120244302681690161",
      "spend": 33151.64,
      "impressions": 238970,
      "frequency": 1.12,
      "link_clicks": 2400,
      "ctr": 1.43,
      "cpm": 138.73,
      "cpc": 9.73,
      "landing_views": 1895,
      "cost_per_landing_view": 17.49,
      "atc": 192,
      "cost_per_atc": 172.66,
      "initiate_checkout": 134,
      "cost_per_initiate_checkout": 247.4,
      "purchases": 59,
      "cac": 561.89,
      "revenue": 69914.04,
      "roas": 2.11,
      "hook_rate": 35.43,
      "thumb_stop_rate": 1.0,
      "video_views_3s": 84678
    },
    {
      "id": "120244302773810161",
      "name": "TV_FRO_VID03 - Copy",
      "status": "ACTIVE",
      "adset": "120244302681690161",
      "spend": 22560.76,
      "impressions": 121603,
      "frequency": 1.27,
      "link_clicks": 1479,
      "ctr": 1.48,
      "cpm": 185.53,
      "cpc": 12.51,
      "landing_views": 1315,
      "cost_per_landing_view": 17.16,
      "atc": 168,
      "cost_per_atc": 134.29,
      "initiate_checkout": 133,
      "cost_per_initiate_checkout": 169.63,
      "purchases": 57,
      "cac": 395.8,
      "revenue": 66058.6,
      "roas": 2.93,
      "hook_rate": 36.77,
      "thumb_stop_rate": 1.22,
      "video_views_3s": 44714
    },
    {
      "id": "120244302773830161",
      "name": "Frozen 01 - Copy",
      "status": "ACTIVE",
      "adset": "120244302681690161",
      "spend": 6946.81,
      "impressions": 43219,
      "frequency": 1.25,
      "link_clicks": 310,
      "ctr": 0.97,
      "cpm": 160.74,
      "cpc": 16.54,
      "landing_views": 212,
      "cost_per_landing_view": 32.77,
      "atc": 32,
      "cost_per_atc": 217.09,
      "initiate_checkout": 34,
      "cost_per_initiate_checkout": 204.32,
      "purchases": 13,
      "cac": 534.37,
      "revenue": 16199.8,
      "roas": 2.33,
      "hook_rate": 13.3,
      "thumb_stop_rate": 0.72,
      "video_views_3s": 5748
    },
    {
      "id": "120244260633650161",
      "name": "TV_FRO_VID01",
      "status": "ACTIVE",
      "adset": "120244260633630161",
      "spend": 8487.99,
      "impressions": 47179,
      "frequency": 1.17,
      "link_clicks": 471,
      "ctr": 1.37,
      "cpm": 179.91,
      "cpc": 13.14,
      "landing_views": 413,
      "cost_per_landing_view": 20.55,
      "atc": 49,
      "cost_per_atc": 173.22,
      "initiate_checkout": 45,
      "cost_per_initiate_checkout": 188.62,
      "purchases": 14,
      "cac": 606.28,
      "revenue": 18880.92,
      "roas": 2.22,
      "hook_rate": 35.37,
      "thumb_stop_rate": 1.0,
      "video_views_3s": 16685
    },
    {
      "id": "120244260633660161",
      "name": "TV_FRO_VID03",
      "status": "ACTIVE",
      "adset": "120244260633630161",
      "spend": 8772.58,
      "impressions": 34950,
      "frequency": 1.33,
      "link_clicks": 584,
      "ctr": 1.96,
      "cpm": 251.0,
      "cpc": 12.79,
      "landing_views": 542,
      "cost_per_landing_view": 16.19,
      "atc": 71,
      "cost_per_atc": 123.56,
      "initiate_checkout": 55,
      "cost_per_initiate_checkout": 159.5,
      "purchases": 25,
      "cac": 350.9,
      "revenue": 30938.64,
      "roas": 3.53,
      "hook_rate": 35.39,
      "thumb_stop_rate": 1.67,
      "video_views_3s": 12368
    },
    {
      "id": "120244260633640161",
      "name": "TV_FRO_VID02",
      "status": "ACTIVE",
      "adset": "120244260633630161",
      "spend": 2.9,
      "impressions": 14,
      "frequency": 1.0,
      "link_clicks": 0,
      "ctr": 0.0,
      "cpm": 207.14,
      "cpc": 0.0,
      "landing_views": 0,
      "cost_per_landing_view": 0,
      "atc": 0,
      "cost_per_atc": 0,
      "initiate_checkout": 0,
      "cost_per_initiate_checkout": 0,
      "purchases": 0,
      "cac": 0,
      "revenue": 0.0,
      "roas": 0.0,
      "hook_rate": 7.14,
      "thumb_stop_rate": 0.0,
      "video_views_3s": 1
    },
    {
      "id": "120244260254740161",
      "name": "Frozen 01",
      "status": "ACTIVE",
      "adset": "120244260254750161",
      "spend": 10869.12,
      "impressions": 47215,
      "frequency": 1.42,
      "link_clicks": 321,
      "ctr": 1.0,
      "cpm": 230.2,
      "cpc": 23.08,
      "landing_views": 282,
      "cost_per_landing_view": 38.54,
      "atc": 77,
      "cost_per_atc": 141.16,
      "initiate_checkout": 57,
      "cost_per_initiate_checkout": 190.69,
      "purchases": 21,
      "cac": 517.58,
      "revenue": 24938.2,
      "roas": 2.29,
      "hook_rate": 11.47,
      "thumb_stop_rate": 0.68,
      "video_views_3s": 5415
    },
    {
      "id": "120244260295280161",
      "name": "Frozen 03",
      "status": "ACTIVE",
      "adset": "120244260254750161",
      "spend": 1031.75,
      "impressions": 3685,
      "frequency": 1.24,
      "link_clicks": 38,
      "ctr": 1.44,
      "cpm": 279.99,
      "cpc": 19.47,
      "landing_views": 29,
      "cost_per_landing_view": 35.58,
      "atc": 8,
      "cost_per_atc": 128.97,
      "initiate_checkout": 9,
      "cost_per_initiate_checkout": 114.64,
      "purchases": 1,
      "cac": 1031.75,
      "revenue": 1620.0,
      "roas": 1.57,
      "hook_rate": 15.74,
      "thumb_stop_rate": 1.03,
      "video_views_3s": 580
    },
    {
      "id": "120244260295270161",
      "name": "Frozen 02",
      "status": "ACTIVE",
      "adset": "120244260254750161",
      "spend": 0.96,
      "impressions": 10,
      "frequency": 1.0,
      "link_clicks": 0,
      "ctr": 0.0,
      "cpm": 96.0,
      "cpc": 0.0,
      "landing_views": 0,
      "cost_per_landing_view": 0,
      "atc": 0,
      "cost_per_atc": 0,
      "initiate_checkout": 0,
      "cost_per_initiate_checkout": 0,
      "purchases": 0,
      "cac": 0,
      "revenue": 0.0,
      "roas": 0.0,
      "hook_rate": 20.0,
      "thumb_stop_rate": 0.0,
      "video_views_3s": 2
    },
    {
      "id": "120244227206140161",
      "name": "TV_FRO_VID04",
      "status": "ACTIVE",
      "adset": "120244227206120161",
      "spend": 39856.73,
      "impressions": 278637,
      "frequency": 1.24,
      "link_clicks": 2789,
      "ctr": 1.34,
      "cpm": 143.04,
      "cpc": 10.67,
      "landing_views": 2237,
      "cost_per_landing_view": 17.82,
      "atc": 245,
      "cost_per_atc": 162.68,
      "initiate_checkout": 204,
      "cost_per_initiate_checkout": 195.38,
      "purchases": 68,
      "cac": 586.13,
      "revenue": 81897.84,
      "roas": 2.05,
      "hook_rate": 23.53,
      "thumb_stop_rate": 1.0,
      "video_views_3s": 65573
    },
    {
      "id": "120244145495780161",
      "name": "TV_FRO_VID03",
      "status": "ACTIVE",
      "adset": "120244145495790161",
      "spend": 31361.09,
      "impressions": 141455,
      "frequency": 1.35,
      "link_clicks": 2054,
      "ctr": 1.72,
      "cpm": 221.7,
      "cpc": 12.85,
      "landing_views": 1869,
      "cost_per_landing_view": 16.78,
      "atc": 229,
      "cost_per_atc": 136.95,
      "initiate_checkout": 178,
      "cost_per_initiate_checkout": 176.19,
      "purchases": 77,
      "cac": 407.29,
      "revenue": 91232.24,
      "roas": 2.91,
      "hook_rate": 36.58,
      "thumb_stop_rate": 1.45,
      "video_views_3s": 51738
    },
    {
      "id": "120244145495800161",
      "name": "TV_FRO_VID02",
      "status": "ACTIVE",
      "adset": "120244145495790161",
      "spend": 416.04,
      "impressions": 2185,
      "frequency": 1.28,
      "link_clicks": 12,
      "ctr": 0.82,
      "cpm": 190.41,
      "cpc": 23.11,
      "landing_views": 7,
      "cost_per_landing_view": 59.43,
      "atc": 1,
      "cost_per_atc": 416.04,
      "initiate_checkout": 1,
      "cost_per_initiate_checkout": 416.04,
      "purchases": 1,
      "cac": 416.04,
      "revenue": 1030.0,
      "roas": 2.48,
      "hook_rate": 17.12,
      "thumb_stop_rate": 0.55,
      "video_views_3s": 374
    },
    {
      "id": "120244145495810161",
      "name": "TV_FRO_VID01",
      "status": "ACTIVE",
      "adset": "120244145495790161",
      "spend": 36603.46,
      "impressions": 237482,
      "frequency": 1.15,
      "link_clicks": 2682,
      "ctr": 1.56,
      "cpm": 154.13,
      "cpc": 9.91,
      "landing_views": 2215,
      "cost_per_landing_view": 16.53,
      "atc": 217,
      "cost_per_atc": 168.68,
      "initiate_checkout": 190,
      "cost_per_initiate_checkout": 192.65,
      "purchases": 80,
      "cac": 457.54,
      "revenue": 88721.4,
      "roas": 2.42,
      "hook_rate": 36.82,
      "thumb_stop_rate": 1.13,
      "video_views_3s": 87447
    },
    {
      "id": "120244074259340161",
      "name": "TV_FRO_VID03",
      "status": "ACTIVE",
      "adset": "120244073473760161",
      "spend": 17468.04,
      "impressions": 96249,
      "frequency": 1.2,
      "link_clicks": 1265,
      "ctr": 1.63,
      "cpm": 181.49,
      "cpc": 11.1,
      "landing_views": 1140,
      "cost_per_landing_view": 15.32,
      "atc": 125,
      "cost_per_atc": 139.74,
      "initiate_checkout": 97,
      "cost_per_initiate_checkout": 180.08,
      "purchases": 40,
      "cac": 436.7,
      "revenue": 47417.2,
      "roas": 2.71,
      "hook_rate": 35.88,
      "thumb_stop_rate": 1.31,
      "video_views_3s": 34530
    },
    {
      "id": "120244073815010161",
      "name": "TV_FRO_VID02",
      "status": "ACTIVE",
      "adset": "120244073473760161",
      "spend": 70.16,
      "impressions": 277,
      "frequency": 1.09,
      "link_clicks": 3,
      "ctr": 0.72,
      "cpm": 253.29,
      "cpc": 35.08,
      "landing_views": 1,
      "cost_per_landing_view": 70.16,
      "atc": 1,
      "cost_per_atc": 70.16,
      "initiate_checkout": 1,
      "cost_per_initiate_checkout": 70.16,
      "purchases": 1,
      "cac": 70.16,
      "revenue": 1798.0,
      "roas": 25.63,
      "hook_rate": 15.52,
      "thumb_stop_rate": 1.08,
      "video_views_3s": 43
    }
  ],
  "spendTrend": [
    {
      "day": "04-11",
      "spend": 95073.05,
      "impressions": 877339,
      "link_clicks": 6878,
      "purchases": 208,
      "revenue": 232235.59,
      "cac": 457.08,
      "roas": 2.44
    },
    {
      "day": "04-12",
      "spend": 127942.92,
      "impressions": 1023714,
      "link_clicks": 8757,
      "purchases": 263,
      "revenue": 289818.91,
      "cac": 486.47,
      "roas": 2.27
    },
    {
      "day": "04-13",
      "spend": 117861.8,
      "impressions": 974925,
      "link_clicks": 8017,
      "purchases": 211,
      "revenue": 225467.37,
      "cac": 558.59,
      "roas": 1.91
    },
    {
      "day": "04-14",
      "spend": 122816.53,
      "impressions": 1057983,
      "link_clicks": 8190,
      "purchases": 220,
      "revenue": 222099.74,
      "cac": 558.26,
      "roas": 1.81
    },
    {
      "day": "04-15",
      "spend": 116466.98,
      "impressions": 981209,
      "link_clicks": 7660,
      "purchases": 202,
      "revenue": 220405.7,
      "cac": 576.57,
      "roas": 1.89
    },
    {
      "day": "04-16",
      "spend": 98840.09,
      "impressions": 741304,
      "link_clicks": 5670,
      "purchases": 126,
      "revenue": 133186.95,
      "cac": 784.45,
      "roas": 1.35
    },
    {
      "day": "04-17",
      "spend": 126250.76,
      "impressions": 867422,
      "link_clicks": 7060,
      "purchases": 214,
      "revenue": 222464.79,
      "cac": 589.96,
      "roas": 1.76
    }
  ],
  "audienceAge": [
    {
      "group": "18-24",
      "reach": 1095011,
      "clicks": 3697,
      "spend": 28885.230000000003,
      "purchases": 33,
      "revenue": 36187.39,
      "frequency": 3.67,
      "count": 3,
      "cac": 875.31,
      "roas": 1.25,
      "avg_frequency": 1.22
    },
    {
      "group": "25-34",
      "reach": 1327709,
      "clicks": 18806,
      "spend": 177259.84,
      "purchases": 324,
      "revenue": 370247.55,
      "frequency": 5.07,
      "count": 3,
      "cac": 547.1,
      "roas": 2.09,
      "avg_frequency": 1.69
    },
    {
      "group": "35-44",
      "reach": 778211,
      "clicks": 21910,
      "spend": 251717.43000000002,
      "purchases": 474,
      "revenue": 527977.71,
      "frequency": 6.210000000000001,
      "count": 3,
      "cac": 531.05,
      "roas": 2.1,
      "avg_frequency": 2.07
    },
    {
      "group": "45-54",
      "reach": 338551,
      "clicks": 13056,
      "spend": 185524.8,
      "purchases": 351,
      "revenue": 371147.08999999997,
      "frequency": 6.88,
      "count": 3,
      "cac": 528.56,
      "roas": 2.0,
      "avg_frequency": 2.29
    },
    {
      "group": "55-64",
      "reach": 141103,
      "clicks": 7721,
      "spend": 112169.46,
      "purchases": 193,
      "revenue": 184438.5,
      "frequency": 7.700000000000001,
      "count": 3,
      "cac": 581.19,
      "roas": 1.64,
      "avg_frequency": 2.57
    },
    {
      "group": "65+",
      "reach": 71034,
      "clicks": 4014,
      "spend": 49549.65000000001,
      "purchases": 69,
      "revenue": 55680.81,
      "frequency": 6.68,
      "count": 3,
      "cac": 718.11,
      "roas": 1.12,
      "avg_frequency": 2.23
    },
    {
      "group": "Unknown",
      "reach": 138,
      "clicks": 158,
      "spend": 145.72,
      "purchases": 0,
      "revenue": 0.0,
      "frequency": 2.1900000000000004,
      "count": 3,
      "cac": 0,
      "roas": 0.0,
      "avg_frequency": 0.73
    }
  ],
  "audienceGender": {
    "male": 82,
    "female": 18
  },
  "geography": [
    {
      "region": "Maharashtra",
      "reach": 1807764,
      "clicks": 20434,
      "impressions": 2617221,
      "spend": 230671.1,
      "purchases": 0,
      "revenue": 78665.7,
      "shopify_orders": 79,
      "revenue_source": "shopify",
      "cac": 0,
      "roas": 0.34,
      "ctr": 0.78
    },
    {
      "region": "Gujarat",
      "reach": 747115,
      "clicks": 12751,
      "impressions": 1262901,
      "spend": 93369.85,
      "purchases": 0,
      "revenue": 33781.0,
      "shopify_orders": 22,
      "revenue_source": "shopify",
      "cac": 0,
      "roas": 0.36,
      "ctr": 1.01
    },
    {
      "region": "Karnataka",
      "reach": 137981,
      "clicks": 4567,
      "impressions": 311532,
      "spend": 72713.93,
      "purchases": 0,
      "revenue": 30482.4,
      "shopify_orders": 29,
      "revenue_source": "shopify",
      "cac": 0,
      "roas": 0.42,
      "ctr": 1.47
    },
    {
      "region": "Delhi",
      "reach": 83585,
      "clicks": 3359,
      "impressions": 197006,
      "spend": 61874.18,
      "purchases": 0,
      "revenue": 14834.95,
      "shopify_orders": 17,
      "revenue_source": "shopify",
      "cac": 0,
      "roas": 0.24,
      "ctr": 1.71
    },
    {
      "region": "Uttar Pradesh",
      "reach": 133834,
      "clicks": 3521,
      "impressions": 269596,
      "spend": 52622.27,
      "purchases": 0,
      "revenue": 22307.3,
      "shopify_orders": 25,
      "revenue_source": "shopify",
      "cac": 0,
      "roas": 0.42,
      "ctr": 1.31
    },
    {
      "region": "Rajasthan",
      "reach": 297084,
      "clicks": 6156,
      "impressions": 611090,
      "spend": 46703.03,
      "purchases": 0,
      "revenue": 4778.0,
      "shopify_orders": 5,
      "revenue_source": "shopify",
      "cac": 0,
      "roas": 0.1,
      "ctr": 1.01
    },
    {
      "region": "Telangana",
      "reach": 80944,
      "clicks": 2664,
      "impressions": 168650,
      "spend": 43766.71,
      "purchases": 0,
      "revenue": 30861.45,
      "shopify_orders": 19,
      "revenue_source": "shopify",
      "cac": 0,
      "roas": 0.71,
      "ctr": 1.58
    },
    {
      "region": "Tamil Nadu",
      "reach": 67536,
      "clicks": 2762,
      "impressions": 155487,
      "spend": 38508.09,
      "purchases": 0,
      "revenue": 8409.9,
      "shopify_orders": 10,
      "revenue_source": "shopify",
      "cac": 0,
      "roas": 0.22,
      "ctr": 1.78
    },
    {
      "region": "Haryana",
      "reach": 71456,
      "clicks": 2103,
      "impressions": 152733,
      "spend": 36795.13,
      "purchases": 0,
      "revenue": 8991.9,
      "shopify_orders": 9,
      "revenue_source": "shopify",
      "cac": 0,
      "roas": 0.24,
      "ctr": 1.38
    },
    {
      "region": "Madhya Pradesh",
      "reach": 116743,
      "clicks": 2703,
      "impressions": 232279,
      "spend": 27090.81,
      "purchases": 0,
      "revenue": 4170.0,
      "shopify_orders": 4,
      "revenue_source": "shopify",
      "cac": 0,
      "roas": 0.15,
      "ctr": 1.16
    },
    {
      "region": "Punjab region",
      "reach": 58691,
      "clicks": 1783,
      "impressions": 125805,
      "spend": 24111.78,
      "purchases": 0,
      "revenue": 0.0,
      "shopify_orders": 0,
      "revenue_source": "meta_pixel",
      "cac": 0,
      "roas": 0.0,
      "ctr": 1.42
    },
    {
      "region": "Chhattisgarh",
      "reach": 48504,
      "clicks": 1187,
      "impressions": 98392,
      "spend": 14179.61,
      "purchases": 0,
      "revenue": 6439.05,
      "shopify_orders": 6,
      "revenue_source": "shopify",
      "cac": 0,
      "roas": 0.45,
      "ctr": 1.21
    },
    {
      "region": "Andhra Pradesh",
      "reach": 34293,
      "clicks": 1045,
      "impressions": 67589,
      "spend": 13669.12,
      "purchases": 0,
      "revenue": 4892.0,
      "shopify_orders": 6,
      "revenue_source": "shopify",
      "cac": 0,
      "roas": 0.36,
      "ctr": 1.55
    },
    {
      "region": "West Bengal",
      "reach": 46885,
      "clicks": 1562,
      "impressions": 87763,
      "spend": 13489.09,
      "purchases": 0,
      "revenue": 3355.0,
      "shopify_orders": 4,
      "revenue_source": "shopify",
      "cac": 0,
      "roas": 0.25,
      "ctr": 1.78
    },
    {
      "region": "Kerala",
      "reach": 23648,
      "clicks": 913,
      "impressions": 48450,
      "spend": 10444.39,
      "purchases": 0,
      "revenue": 930.0,
      "shopify_orders": 1,
      "revenue_source": "shopify",
      "cac": 0,
      "roas": 0.09,
      "ctr": 1.88
    },
    {
      "region": "Uttarakhand",
      "reach": 16827,
      "clicks": 563,
      "impressions": 35243,
      "spend": 7700.02,
      "purchases": 0,
      "revenue": 5348.0,
      "shopify_orders": 5,
      "revenue_source": "shopify",
      "cac": 0,
      "roas": 0.69,
      "ctr": 1.6
    },
    {
      "region": "Goa",
      "reach": 16746,
      "clicks": 625,
      "impressions": 36732,
      "spend": 7418.42,
      "purchases": 0,
      "revenue": 3649.0,
      "shopify_orders": 4,
      "revenue_source": "shopify",
      "cac": 0,
      "roas": 0.49,
      "ctr": 1.7
    },
    {
      "region": "Chandigarh",
      "reach": 6559,
      "clicks": 238,
      "impressions": 14763,
      "spend": 4544.36,
      "purchases": 0,
      "revenue": 0.0,
      "shopify_orders": 0,
      "revenue_source": "meta_pixel",
      "cac": 0,
      "roas": 0.0,
      "ctr": 1.61
    },
    {
      "region": "Himachal Pradesh",
      "reach": 8397,
      "clicks": 229,
      "impressions": 16701,
      "spend": 2920.95,
      "purchases": 0,
      "revenue": 0.0,
      "shopify_orders": 0,
      "revenue_source": "meta_pixel",
      "cac": 0,
      "roas": 0.0,
      "ctr": 1.37
    },
    {
      "region": "Andaman and Nicobar Islands",
      "reach": 2125,
      "clicks": 68,
      "impressions": 5219,
      "spend": 1158.5,
      "purchases": 0,
      "revenue": 0.0,
      "shopify_orders": 0,
      "revenue_source": "meta_pixel",
      "cac": 0,
      "roas": 0.0,
      "ctr": 1.3
    },
    {
      "region": "Puducherry",
      "reach": 1707,
      "clicks": 64,
      "impressions": 3610,
      "spend": 881.66,
      "purchases": 0,
      "revenue": 0.0,
      "shopify_orders": 0,
      "revenue_source": "meta_pixel",
      "cac": 0,
      "roas": 0.0,
      "ctr": 1.77
    },
    {
      "region": "Dadra and Nagar Haveli",
      "reach": 2177,
      "clicks": 56,
      "impressions": 4607,
      "spend": 516.59,
      "purchases": 0,
      "revenue": 0.0,
      "shopify_orders": 0,
      "revenue_source": "meta_pixel",
      "cac": 0,
      "roas": 0.0,
      "ctr": 1.22
    },
    {
      "region": "Unknown",
      "reach": 295,
      "clicks": 5,
      "impressions": 360,
      "spend": 68.09,
      "purchases": 0,
      "revenue": 0.0,
      "shopify_orders": 0,
      "revenue_source": "meta_pixel",
      "cac": 0,
      "roas": 0.0,
      "ctr": 1.39
    },
    {
      "region": "Lakshadweep",
      "reach": 73,
      "clicks": 4,
      "impressions": 167,
      "spend": 34.43,
      "purchases": 0,
      "revenue": 0.0,
      "shopify_orders": 0,
      "revenue_source": "meta_pixel",
      "cac": 0,
      "roas": 0.0,
      "ctr": 2.4
    }
  ],
  "placements": [
    {
      "platform": "instagram",
      "position": "instagram_reels",
      "spend": 295875.68,
      "impressions": 3014679,
      "clicks": 21015,
      "reach": 2047081,
      "purchases": 550,
      "revenue": 586382.97,
      "cac": 537.96,
      "ctr": 0.7,
      "roas": 1.98
    },
    {
      "platform": "instagram",
      "position": "feed",
      "spend": 177351.35,
      "impressions": 1412072,
      "clicks": 10512,
      "reach": 1017067,
      "purchases": 315,
      "revenue": 345963.95,
      "cac": 563.02,
      "ctr": 0.74,
      "roas": 1.95
    },
    {
      "platform": "facebook",
      "position": "feed",
      "spend": 151804.97,
      "impressions": 905398,
      "clicks": 17996,
      "reach": 558780,
      "purchases": 271,
      "revenue": 280382.73,
      "cac": 560.17,
      "ctr": 1.99,
      "roas": 1.85
    },
    {
      "platform": "facebook",
      "position": "facebook_reels",
      "spend": 87396.44,
      "impressions": 559604,
      "clicks": 7691,
      "reach": 276621,
      "purchases": 173,
      "revenue": 175339.31,
      "cac": 505.18,
      "ctr": 1.37,
      "roas": 2.01
    },
    {
      "platform": "instagram",
      "position": "instagram_stories",
      "spend": 54973.33,
      "impressions": 333202,
      "clicks": 5441,
      "reach": 238530,
      "purchases": 84,
      "revenue": 95326.01,
      "cac": 654.44,
      "ctr": 1.63,
      "roas": 1.73
    },
    {
      "platform": "facebook",
      "position": "facebook_stories",
      "spend": 19752.13,
      "impressions": 66937,
      "clicks": 1863,
      "reach": 45722,
      "purchases": 30,
      "revenue": 34831.59,
      "cac": 658.4,
      "ctr": 2.78,
      "roas": 1.76
    },
    {
      "platform": "facebook",
      "position": "instream_video",
      "spend": 5812.99,
      "impressions": 38430,
      "clicks": 636,
      "reach": 13150,
      "purchases": 7,
      "revenue": 15958.0,
      "cac": 830.43,
      "ctr": 1.65,
      "roas": 2.75
    },
    {
      "platform": "audience_network",
      "position": "rewarded_video",
      "spend": 5505.07,
      "impressions": 11717,
      "clicks": 1974,
      "reach": 2743,
      "purchases": 3,
      "revenue": 2390.0,
      "cac": 1835.02,
      "ctr": 16.85,
      "roas": 0.43
    },
    {
      "platform": "audience_network",
      "position": "an_classic",
      "spend": 4474.69,
      "impressions": 14244,
      "clicks": 1806,
      "reach": 4003,
      "purchases": 8,
      "revenue": 7134.5,
      "cac": 559.34,
      "ctr": 12.68,
      "roas": 1.59
    },
    {
      "platform": "threads",
      "position": "threads_feed",
      "spend": 737.49,
      "impressions": 14159,
      "clicks": 103,
      "reach": 12915,
      "purchases": 0,
      "revenue": 0.0,
      "cac": 0,
      "ctr": 0.73,
      "roas": 0.0
    },
    {
      "platform": "facebook",
      "position": "marketplace",
      "spend": 345.62,
      "impressions": 3972,
      "clicks": 37,
      "reach": 2412,
      "purchases": 1,
      "revenue": 720.0,
      "cac": 345.62,
      "ctr": 0.93,
      "roas": 2.08
    },
    {
      "platform": "instagram",
      "position": "instagram_explore_grid_home",
      "spend": 300.58,
      "impressions": 72541,
      "clicks": 23,
      "reach": 69284,
      "purchases": 0,
      "revenue": 0.0,
      "cac": 0,
      "ctr": 0.03,
      "roas": 0.0
    },
    {
      "platform": "facebook",
      "position": "search",
      "spend": 267.29,
      "impressions": 1829,
      "clicks": 34,
      "reach": 1575,
      "purchases": 1,
      "revenue": 630.0,
      "cac": 267.29,
      "ctr": 1.86,
      "roas": 2.36
    },
    {
      "platform": "facebook",
      "position": "facebook_reels_overlay",
      "spend": 183.09,
      "impressions": 4869,
      "clicks": 26,
      "reach": 2396,
      "purchases": 1,
      "revenue": 620.0,
      "cac": 183.09,
      "ctr": 0.53,
      "roas": 3.39
    },
    {
      "platform": "facebook",
      "position": "facebook_notification",
      "spend": 176.9,
      "impressions": 532,
      "clicks": 21,
      "reach": 456,
      "purchases": 0,
      "revenue": 0.0,
      "cac": 0,
      "ctr": 3.95,
      "roas": 0.0
    },
    {
      "platform": "whatsapp",
      "position": "status",
      "spend": 142.31,
      "impressions": 65747,
      "clicks": 158,
      "reach": 9,
      "purchases": 0,
      "revenue": 0.0,
      "cac": 0,
      "ctr": 0.24,
      "roas": 0.0
    },
    {
      "platform": "facebook",
      "position": "facebook_profile_feed",
      "spend": 64.22,
      "impressions": 1003,
      "clicks": 11,
      "reach": 921,
      "purchases": 0,
      "revenue": 0.0,
      "cac": 0,
      "ctr": 1.1,
      "roas": 0.0
    },
    {
      "platform": "facebook",
      "position": "right_hand_column",
      "spend": 51.54,
      "impressions": 2119,
      "clicks": 1,
      "reach": 500,
      "purchases": 0,
      "revenue": 0.0,
      "cac": 0,
      "ctr": 0.05,
      "roas": 0.0
    },
    {
      "platform": "instagram",
      "position": "instagram_search",
      "spend": 25.33,
      "impressions": 763,
      "clicks": 4,
      "reach": 757,
      "purchases": 0,
      "revenue": 0.0,
      "cac": 0,
      "ctr": 0.52,
      "roas": 0.0
    },
    {
      "platform": "instagram",
      "position": "instagram_explore",
      "spend": 11.04,
      "impressions": 71,
      "clicks": 1,
      "reach": 55,
      "purchases": 0,
      "revenue": 0.0,
      "cac": 0,
      "ctr": 1.41,
      "roas": 0.0
    },
    {
      "platform": "facebook",
      "position": "biz_disco_feed",
      "spend": 1.25,
      "impressions": 7,
      "clicks": 2,
      "reach": 7,
      "purchases": 0,
      "revenue": 0.0,
      "cac": 0,
      "ctr": 28.57,
      "roas": 0.0
    },
    {
      "platform": "messenger",
      "position": "messenger_stories",
      "spend": 0.0,
      "impressions": 1,
      "clicks": 0,
      "reach": 1,
      "purchases": 0,
      "revenue": 0.0,
      "cac": 0,
      "ctr": 0.0,
      "roas": 0
    },
    {
      "platform": "unknown",
      "position": "unknown",
      "spend": 0.0,
      "impressions": 0,
      "clicks": 7,
      "reach": 0,
      "purchases": 0,
      "revenue": 0.0,
      "cac": 0,
      "ctr": 0,
      "roas": 0
    }
  ],
  "hours": [
    {
      "hour": "00",
      "spend": 38808.79,
      "impressions": 308163,
      "clicks": 3328,
      "purchases": 51,
      "cac": 760.96
    },
    {
      "hour": "01",
      "spend": 17361.76,
      "impressions": 140936,
      "clicks": 1453,
      "purchases": 34,
      "cac": 510.64
    },
    {
      "hour": "02",
      "spend": 9072.2,
      "impressions": 72599,
      "clicks": 704,
      "purchases": 10,
      "cac": 907.22
    },
    {
      "hour": "03",
      "spend": 5668.25,
      "impressions": 41880,
      "clicks": 369,
      "purchases": 5,
      "cac": 1133.65
    },
    {
      "hour": "04",
      "spend": 4644.56,
      "impressions": 30243,
      "clicks": 301,
      "purchases": 5,
      "cac": 928.91
    },
    {
      "hour": "05",
      "spend": 6300.37,
      "impressions": 52778,
      "clicks": 398,
      "purchases": 9,
      "cac": 700.04
    },
    {
      "hour": "06",
      "spend": 11756.14,
      "impressions": 122011,
      "clicks": 818,
      "purchases": 16,
      "cac": 734.76
    },
    {
      "hour": "07",
      "spend": 20784.93,
      "impressions": 150976,
      "clicks": 1299,
      "purchases": 15,
      "cac": 1385.66
    },
    {
      "hour": "08",
      "spend": 32626.14,
      "impressions": 231376,
      "clicks": 2329,
      "purchases": 57,
      "cac": 572.39
    },
    {
      "hour": "09",
      "spend": 41416.87,
      "impressions": 291608,
      "clicks": 2979,
      "purchases": 62,
      "cac": 668.01
    },
    {
      "hour": "10",
      "spend": 43595.42,
      "impressions": 317520,
      "clicks": 3370,
      "purchases": 62,
      "cac": 703.15
    },
    {
      "hour": "11",
      "spend": 41942.76,
      "impressions": 308926,
      "clicks": 3635,
      "purchases": 84,
      "cac": 499.32
    },
    {
      "hour": "12",
      "spend": 41793.78,
      "impressions": 324973,
      "clicks": 3768,
      "purchases": 89,
      "cac": 469.59
    },
    {
      "hour": "13",
      "spend": 43079.41,
      "impressions": 349380,
      "clicks": 4038,
      "purchases": 96,
      "cac": 448.74
    },
    {
      "hour": "14",
      "spend": 42636.49,
      "impressions": 382668,
      "clicks": 4099,
      "purchases": 89,
      "cac": 479.06
    },
    {
      "hour": "15",
      "spend": 40516.86,
      "impressions": 307754,
      "clicks": 3744,
      "purchases": 74,
      "cac": 547.53
    },
    {
      "hour": "16",
      "spend": 39196.2,
      "impressions": 299264,
      "clicks": 3544,
      "purchases": 91,
      "cac": 430.73
    },
    {
      "hour": "17",
      "spend": 39491.96,
      "impressions": 313882,
      "clicks": 3396,
      "purchases": 98,
      "cac": 402.98
    },
    {
      "hour": "18",
      "spend": 36919.2,
      "impressions": 303369,
      "clicks": 3213,
      "purchases": 73,
      "cac": 505.74
    },
    {
      "hour": "19",
      "spend": 36327.98,
      "impressions": 305905,
      "clicks": 3295,
      "purchases": 64,
      "cac": 567.62
    },
    {
      "hour": "20",
      "spend": 71144.58,
      "impressions": 534964,
      "clicks": 6076,
      "purchases": 102,
      "cac": 697.5
    },
    {
      "hour": "21",
      "spend": 49464.02,
      "impressions": 458624,
      "clicks": 4725,
      "purchases": 90,
      "cac": 549.6
    },
    {
      "hour": "22",
      "spend": 50015.84,
      "impressions": 477819,
      "clicks": 4708,
      "purchases": 89,
      "cac": 561.98
    },
    {
      "hour": "23",
      "spend": 40687.62,
      "impressions": 396278,
      "clicks": 3773,
      "purchases": 79,
      "cac": 515.03
    }
  ],
  "pacing": {
    "days_elapsed": 18,
    "days_remaining": 12,
    "spend_to_date": 805252.13,
    "daily_avg": 44736.23,
    "projected_month": 1342086.9,
    "purchases_to_date": 1603,
    "projected_purchases": 2672,
    "projected_cac": 502.34
  },
  "lastUpdated": "2026-04-18 11:32 IST",
  "dateRange": "last_7d",
  "shopify_connected": true
}