{
  "summary": {
    "spend": 2104087.23,
    "impressions": 18172784,
    "clicks": 194052,
    "link_clicks": 140405,
    "ctr": 1.07,
    "cpm": 115.78,
    "reach": 7780176,
    "conversions": 3192,
    "revenue": 3612967.78,
    "revenue_source": "shopify",
    "shopify_orders": 3842,
    "roas": 1.72,
    "cac": 659.18,
    "landing_views": 105037,
    "add_to_cart": 16915,
    "frequency": 2.34
  },
  "campaigns": [
    {
      "id": "120243993730640161",
      "name": "CM | Amazon LP | Jamun Strips & Cubes | 010426",
      "status": "ACTIVE",
      "objective": "OUTCOME_SALES",
      "spend": 715.99,
      "impressions": 4178,
      "link_clicks": 49,
      "ctr": 1.58,
      "cpm": 171.37,
      "reach": 3272,
      "roas": 0.88,
      "cac": 715.99,
      "purchases": 1,
      "revenue": 630.0,
      "frequency": 1.28,
      "atc": 6,
      "atc_abandon_rate": 83.3,
      "funnel": {
        "reach": 3272,
        "impressions": 4178,
        "link_clicks": 49,
        "landing_views": 11,
        "add_to_cart": 6,
        "purchases": 1,
        "dropoffs": {
          "impressions_to_link_clicks": 1.17,
          "link_clicks_to_landing": 22.4,
          "landing_to_cart": 54.5,
          "cart_to_purchase": 16.7
        }
      }
    },
    {
      "id": "120243432146470161",
      "name": "TOF_SCALING_WELLNESS_CBO_230326",
      "status": "PAUSED",
      "objective": "OUTCOME_SALES",
      "spend": 14943.74,
      "impressions": 24835,
      "link_clicks": 442,
      "ctr": 2.44,
      "cpm": 601.72,
      "reach": 20221,
      "roas": 0.87,
      "cac": 747.19,
      "purchases": 20,
      "revenue": 12939.0,
      "frequency": 1.23,
      "atc": 128,
      "atc_abandon_rate": 84.4,
      "funnel": {
        "reach": 20221,
        "impressions": 24835,
        "link_clicks": 442,
        "landing_views": 363,
        "add_to_cart": 128,
        "purchases": 20,
        "dropoffs": {
          "impressions_to_link_clicks": 1.78,
          "link_clicks_to_landing": 82.1,
          "landing_to_cart": 35.3,
          "cart_to_purchase": 15.6
        }
      }
    },
    {
      "id": "120243156192820161",
      "name": "TOF_ABO_Regional_Campaign_170326",
      "status": "ACTIVE",
      "objective": "OUTCOME_SALES",
      "spend": 16380.28,
      "impressions": 174486,
      "link_clicks": 1519,
      "ctr": 1.23,
      "cpm": 93.88,
      "reach": 119003,
      "roas": 1.82,
      "cac": 546.01,
      "purchases": 30,
      "revenue": 29796.0,
      "frequency": 1.47,
      "atc": 186,
      "atc_abandon_rate": 83.9,
      "funnel": {
        "reach": 119003,
        "impressions": 174486,
        "link_clicks": 1519,
        "landing_views": 1171,
        "add_to_cart": 186,
        "purchases": 30,
        "dropoffs": {
          "impressions_to_link_clicks": 0.87,
          "link_clicks_to_landing": 77.1,
          "landing_to_cart": 15.9,
          "cart_to_purchase": 16.1
        }
      }
    },
    {
      "id": "120243131623440161",
      "name": "TOF_ WhatsApp lead - B2B_170326",
      "status": "ACTIVE",
      "objective": "OUTCOME_LEADS",
      "spend": 33672.37,
      "impressions": 1589907,
      "link_clicks": 6692,
      "ctr": 0.81,
      "cpm": 21.18,
      "reach": 371781,
      "roas": 0.02,
      "cac": 33672.37,
      "purchases": 1,
      "revenue": 660.0,
      "frequency": 4.28,
      "atc": 3,
      "atc_abandon_rate": 66.7,
      "funnel": {
        "reach": 371781,
        "impressions": 1589907,
        "link_clicks": 6692,
        "landing_views": 13,
        "add_to_cart": 3,
        "purchases": 1,
        "dropoffs": {
          "impressions_to_link_clicks": 0.42,
          "link_clicks_to_landing": 0.2,
          "landing_to_cart": 23.1,
          "cart_to_purchase": 33.3
        }
      }
    },
    {
      "id": "120242935172170161",
      "name": "TOF_AD_CTWinners_140326",
      "status": "PAUSED",
      "objective": "OUTCOME_SALES",
      "spend": 0.0,
      "impressions": 0,
      "link_clicks": 0,
      "ctr": 0.0,
      "cpm": 0.0,
      "reach": 0,
      "roas": 0,
      "cac": 0,
      "purchases": 0,
      "revenue": 0.0,
      "frequency": 0.0,
      "atc": 0,
      "atc_abandon_rate": 0,
      "funnel": {
        "reach": 0,
        "impressions": 0,
        "link_clicks": 0,
        "landing_views": 0,
        "add_to_cart": 0,
        "purchases": 0,
        "dropoffs": {
          "impressions_to_link_clicks": 0,
          "link_clicks_to_landing": 0,
          "landing_to_cart": 0,
          "cart_to_purchase": 0
        }
      }
    },
    {
      "id": "120242929159510161",
      "name": "TOF_Jam&Sauce_ABO_140326",
      "status": "ACTIVE",
      "objective": "OUTCOME_SALES",
      "spend": 81939.91,
      "impressions": 261067,
      "link_clicks": 4793,
      "ctr": 2.21,
      "cpm": 313.87,
      "reach": 133554,
      "roas": 1.06,
      "cac": 758.7,
      "purchases": 108,
      "revenue": 86529.0,
      "frequency": 1.95,
      "atc": 705,
      "atc_abandon_rate": 84.7,
      "funnel": {
        "reach": 133554,
        "impressions": 261067,
        "link_clicks": 4793,
        "landing_views": 3573,
        "add_to_cart": 705,
        "purchases": 108,
        "dropoffs": {
          "impressions_to_link_clicks": 1.84,
          "link_clicks_to_landing": 74.5,
          "landing_to_cart": 19.7,
          "cart_to_purchase": 15.3
        }
      }
    },
    {
      "id": "120242867608740161",
      "name": "TOF_WELLNESS_ABO_130326",
      "status": "ACTIVE",
      "objective": "OUTCOME_SALES",
      "spend": 203061.34,
      "impressions": 604613,
      "link_clicks": 9304,
      "ctr": 1.88,
      "cpm": 335.85,
      "reach": 216981,
      "roas": 1.43,
      "cac": 609.79,
      "purchases": 333,
      "revenue": 289511.25,
      "frequency": 2.79,
      "atc": 1921,
      "atc_abandon_rate": 82.7,
      "funnel": {
        "reach": 216981,
        "impressions": 604613,
        "link_clicks": 9304,
        "landing_views": 7191,
        "add_to_cart": 1921,
        "purchases": 333,
        "dropoffs": {
          "impressions_to_link_clicks": 1.54,
          "link_clicks_to_landing": 77.3,
          "landing_to_cart": 26.7,
          "cart_to_purchase": 17.3
        }
      }
    },
    {
      "id": "120242865698210161",
      "name": "TOF_WELLNESS_ABO_130326",
      "status": "PAUSED",
      "objective": "OUTCOME_SALES",
      "spend": 0.0,
      "impressions": 0,
      "link_clicks": 0,
      "ctr": 0.0,
      "cpm": 0.0,
      "reach": 0,
      "roas": 0,
      "cac": 0,
      "purchases": 0,
      "revenue": 0.0,
      "frequency": 0.0,
      "atc": 0,
      "atc_abandon_rate": 0,
      "funnel": {
        "reach": 0,
        "impressions": 0,
        "link_clicks": 0,
        "landing_views": 0,
        "add_to_cart": 0,
        "purchases": 0,
        "dropoffs": {
          "impressions_to_link_clicks": 0,
          "link_clicks_to_landing": 0,
          "landing_to_cart": 0,
          "cart_to_purchase": 0
        }
      }
    },
    {
      "id": "120242067966070161",
      "name": "TOF | Brand Awareness",
      "status": "ACTIVE",
      "objective": "OUTCOME_AWARENESS",
      "spend": 13981.63,
      "impressions": 6995557,
      "link_clicks": 11,
      "ctr": 0.09,
      "cpm": 2.0,
      "reach": 5343068,
      "roas": 0,
      "cac": 0,
      "purchases": 0,
      "revenue": 0.0,
      "frequency": 1.31,
      "atc": 4,
      "atc_abandon_rate": 100.0,
      "funnel": {
        "reach": 5343068,
        "impressions": 6995557,
        "link_clicks": 11,
        "landing_views": 0,
        "add_to_cart": 4,
        "purchases": 0,
        "dropoffs": {
          "impressions_to_link_clicks": 0.0,
          "link_clicks_to_landing": 0.0,
          "landing_to_cart": 0,
          "cart_to_purchase": 0.0
        }
      }
    },
    {
      "id": "120239860888480161",
      "name": "TOF | WhatsApp lead - B2B | 16/1/2026",
      "status": "PAUSED",
      "objective": "OUTCOME_LEADS",
      "spend": 0.0,
      "impressions": 0,
      "link_clicks": 0,
      "ctr": 0.0,
      "cpm": 0.0,
      "reach": 0,
      "roas": 0,
      "cac": 0,
      "purchases": 0,
      "revenue": 0.0,
      "frequency": 0.0,
      "atc": 0,
      "atc_abandon_rate": 0,
      "funnel": {
        "reach": 0,
        "impressions": 0,
        "link_clicks": 0,
        "landing_views": 0,
        "add_to_cart": 0,
        "purchases": 0,
        "dropoffs": {
          "impressions_to_link_clicks": 0,
          "link_clicks_to_landing": 0,
          "landing_to_cart": 0,
          "cart_to_purchase": 0
        }
      }
    },
    {
      "id": "120239115875370161",
      "name": "CM | Nutrition Specific | 13/12/25",
      "status": "PAUSED",
      "objective": "OUTCOME_SALES",
      "spend": 50745.97,
      "impressions": 94119,
      "link_clicks": 1337,
      "ctr": 1.8,
      "cpm": 539.17,
      "reach": 61950,
      "roas": 1.28,
      "cac": 957.47,
      "purchases": 53,
      "revenue": 65154.5,
      "frequency": 1.52,
      "atc": 240,
      "atc_abandon_rate": 77.9,
      "funnel": {
        "reach": 61950,
        "impressions": 94119,
        "link_clicks": 1337,
        "landing_views": 1098,
        "add_to_cart": 240,
        "purchases": 53,
        "dropoffs": {
          "impressions_to_link_clicks": 1.42,
          "link_clicks_to_landing": 82.1,
          "landing_to_cart": 21.9,
          "cart_to_purchase": 22.1
        }
      }
    },
    {
      "id": "120239112575060161",
      "name": "A+S | Creative test - Mixed Products | 1/4/2025",
      "status": "PAUSED",
      "objective": "OUTCOME_SALES",
      "spend": 78516.75,
      "impressions": 338010,
      "link_clicks": 6570,
      "ctr": 2.13,
      "cpm": 232.29,
      "reach": 156119,
      "roas": 1.37,
      "cac": 643.58,
      "purchases": 122,
      "revenue": 107366.2,
      "frequency": 2.17,
      "atc": 594,
      "atc_abandon_rate": 79.5,
      "funnel": {
        "reach": 156119,
        "impressions": 338010,
        "link_clicks": 6570,
        "landing_views": 4784,
        "add_to_cart": 594,
        "purchases": 122,
        "dropoffs": {
          "impressions_to_link_clicks": 1.94,
          "link_clicks_to_landing": 72.8,
          "landing_to_cart": 12.4,
          "cart_to_purchase": 20.5
        }
      }
    },
    {
      "id": "120239047825250161",
      "name": "CM | Jamun Strips & Cubes | 06/08/25",
      "status": "ACTIVE",
      "objective": "OUTCOME_SALES",
      "spend": 255209.28,
      "impressions": 834817,
      "link_clicks": 14418,
      "ctr": 2.39,
      "cpm": 305.71,
      "reach": 508646,
      "roas": 1.86,
      "cac": 440.78,
      "purchases": 579,
      "revenue": 473495.75,
      "frequency": 1.64,
      "atc": 3463,
      "atc_abandon_rate": 83.3,
      "funnel": {
        "reach": 508646,
        "impressions": 834817,
        "link_clicks": 14418,
        "landing_views": 12334,
        "add_to_cart": 3463,
        "purchases": 579,
        "dropoffs": {
          "impressions_to_link_clicks": 1.73,
          "link_clicks_to_landing": 85.5,
          "landing_to_cart": 28.1,
          "cart_to_purchase": 16.7
        }
      }
    },
    {
      "id": "120239047503140161",
      "name": "TOF | New Video Creatives Test | 28/05/25",
      "status": "ACTIVE",
      "objective": "OUTCOME_SALES",
      "spend": 311360.0,
      "impressions": 1602362,
      "link_clicks": 16471,
      "ctr": 1.29,
      "cpm": 194.31,
      "reach": 504890,
      "roas": 1.53,
      "cac": 626.48,
      "purchases": 497,
      "revenue": 477680.06,
      "frequency": 3.17,
      "atc": 2713,
      "atc_abandon_rate": 81.7,
      "funnel": {
        "reach": 504890,
        "impressions": 1602362,
        "link_clicks": 16471,
        "landing_views": 13113,
        "add_to_cart": 2713,
        "purchases": 497,
        "dropoffs": {
          "impressions_to_link_clicks": 1.03,
          "link_clicks_to_landing": 79.6,
          "landing_to_cart": 20.7,
          "cart_to_purchase": 18.3
        }
      }
    },
    {
      "id": "120239046978990161",
      "name": "TOF | ROAS Cap - Performers | 10/9/2025",
      "status": "PAUSED",
      "objective": "OUTCOME_SALES",
      "spend": 0.0,
      "impressions": 0,
      "link_clicks": 0,
      "ctr": 0.0,
      "cpm": 0.0,
      "reach": 0,
      "roas": 0,
      "cac": 0,
      "purchases": 0,
      "revenue": 0.0,
      "frequency": 0.0,
      "atc": 0,
      "atc_abandon_rate": 0,
      "funnel": {
        "reach": 0,
        "impressions": 0,
        "link_clicks": 0,
        "landing_views": 0,
        "add_to_cart": 0,
        "purchases": 0,
        "dropoffs": {
          "impressions_to_link_clicks": 0,
          "link_clicks_to_landing": 0,
          "landing_to_cart": 0,
          "cart_to_purchase": 0
        }
      }
    },
    {
      "id": "120239044894930161",
      "name": "CM | Frozen Specific | 05/12/2025",
      "status": "ACTIVE",
      "objective": "OUTCOME_SALES",
      "spend": 492015.98,
      "impressions": 2856019,
      "link_clicks": 41593,
      "ctr": 2.1,
      "cpm": 172.27,
      "reach": 1167446,
      "roas": 1.17,
      "cac": 750.02,
      "purchases": 656,
      "revenue": 577247.75,
      "frequency": 2.45,
      "atc": 3032,
      "atc_abandon_rate": 78.4,
      "funnel": {
        "reach": 1167446,
        "impressions": 2856019,
        "link_clicks": 41593,
        "landing_views": 33062,
        "add_to_cart": 3032,
        "purchases": 656,
        "dropoffs": {
          "impressions_to_link_clicks": 1.46,
          "link_clicks_to_landing": 79.5,
          "landing_to_cart": 9.2,
          "cart_to_purchase": 21.6
        }
      }
    },
    {
      "id": "120239044078200161",
      "name": "TOF | Catalog sales - All products | 21/11/2025",
      "status": "ACTIVE",
      "objective": "OUTCOME_SALES",
      "spend": 346664.64,
      "impressions": 1779341,
      "link_clicks": 21422,
      "ctr": 1.46,
      "cpm": 194.83,
      "reach": 671605,
      "roas": 1.41,
      "cac": 694.72,
      "purchases": 499,
      "revenue": 488788.18,
      "frequency": 2.65,
      "atc": 2506,
      "atc_abandon_rate": 80.1,
      "funnel": {
        "reach": 671605,
        "impressions": 1779341,
        "link_clicks": 21422,
        "landing_views": 17072,
        "add_to_cart": 2506,
        "purchases": 499,
        "dropoffs": {
          "impressions_to_link_clicks": 1.2,
          "link_clicks_to_landing": 79.7,
          "landing_to_cart": 14.7,
          "cart_to_purchase": 19.9
        }
      }
    },
    {
      "id": "120239042395530161",
      "name": "CM | Brand Specific | 04/12/25",
      "status": "ACTIVE",
      "objective": "OUTCOME_SALES",
      "spend": 204879.35,
      "impressions": 1013473,
      "link_clicks": 15784,
      "ctr": 1.94,
      "cpm": 202.16,
      "reach": 390665,
      "roas": 1.37,
      "cac": 699.25,
      "purchases": 293,
      "revenue": 280147.7,
      "frequency": 2.59,
      "atc": 1414,
      "atc_abandon_rate": 79.3,
      "funnel": {
        "reach": 390665,
        "impressions": 1013473,
        "link_clicks": 15784,
        "landing_views": 11252,
        "add_to_cart": 1414,
        "purchases": 293,
        "dropoffs": {
          "impressions_to_link_clicks": 1.56,
          "link_clicks_to_landing": 71.3,
          "landing_to_cart": 12.6,
          "cart_to_purchase": 20.7
        }
      }
    },
    {
      "id": "120223421188820161",
      "name": "A+S | Jamun Strip - Pilot test | 24/4/2025 Campaign",
      "status": "PAUSED",
      "objective": "OUTCOME_SALES",
      "spend": 0.0,
      "impressions": 0,
      "link_clicks": 0,
      "ctr": 0.0,
      "cpm": 0.0,
      "reach": 0,
      "roas": 0,
      "cac": 0,
      "purchases": 0,
      "revenue": 0.0,
      "frequency": 0.0,
      "atc": 0,
      "atc_abandon_rate": 0,
      "funnel": {
        "reach": 0,
        "impressions": 0,
        "link_clicks": 0,
        "landing_views": 0,
        "add_to_cart": 0,
        "purchases": 0,
        "dropoffs": {
          "impressions_to_link_clicks": 0,
          "link_clicks_to_landing": 0,
          "landing_to_cart": 0,
          "cart_to_purchase": 0
        }
      }
    },
    {
      "id": "120221988443340161",
      "name": "TOF | ROAS Cap - Strips and Seed powder | 12/4/2025",
      "status": "PAUSED",
      "objective": "OUTCOME_SALES",
      "spend": 0.0,
      "impressions": 0,
      "link_clicks": 0,
      "ctr": 0.0,
      "cpm": 0.0,
      "reach": 0,
      "roas": 0,
      "cac": 0,
      "purchases": 0,
      "revenue": 0.0,
      "frequency": 0.0,
      "atc": 0,
      "atc_abandon_rate": 0,
      "funnel": {
        "reach": 0,
        "impressions": 0,
        "link_clicks": 0,
        "landing_views": 0,
        "add_to_cart": 0,
        "purchases": 0,
        "dropoffs": {
          "impressions_to_link_clicks": 0,
          "link_clicks_to_landing": 0,
          "landing_to_cart": 0,
          "cart_to_purchase": 0
        }
      }
    }
  ],
  "adsets": [
    {
      "id": "120244145495790161",
      "name": "All India | Frozen Shots | VDCT | 030426",
      "status": "ACTIVE",
      "daily_budget": 2500.0,
      "spend": 0.0,
      "impressions": 0,
      "link_clicks": 0,
      "purchases": 0,
      "cac": 0,
      "atc": 0,
      "atc_abandon_rate": 0,
      "frequency": 0.0,
      "age": "18\u201365",
      "gender": "All"
    },
    {
      "id": "120244073473760161",
      "name": "All India | Frozen Shots | VDCT | 020426",
      "status": "ACTIVE",
      "daily_budget": 1000.0,
      "spend": 467.5,
      "impressions": 1921,
      "link_clicks": 52,
      "purchases": 4,
      "cac": 116.88,
      "atc": 19,
      "atc_abandon_rate": 78.9,
      "frequency": 1.01,
      "age": "18\u201365",
      "gender": "All"
    },
    {
      "id": "120243993730690161",
      "name": "Amazon LP | Advantage+",
      "status": "ACTIVE",
      "daily_budget": 0.0,
      "spend": 653.59,
      "impressions": 3927,
      "link_clicks": 45,
      "purchases": 1,
      "cac": 653.59,
      "atc": 6,
      "atc_abandon_rate": 83.3,
      "frequency": 1.26,
      "age": "18\u201365",
      "gender": "All"
    },
    {
      "id": "120243993730680161",
      "name": "Amazon LP | Advantage+ | Strips video",
      "status": "ACTIVE",
      "daily_budget": 0.0,
      "spend": 62.4,
      "impressions": 251,
      "link_clicks": 4,
      "purchases": 0,
      "cac": 0,
      "atc": 0,
      "atc_abandon_rate": 0,
      "frequency": 1.19,
      "age": "18\u201365",
      "gender": "All"
    },
    {
      "id": "120243754651990161",
      "name": "Ahmedabad | UGC | Batch 05",
      "status": "PAUSED",
      "daily_budget": 500.0,
      "spend": 1240.67,
      "impressions": 6658,
      "link_clicks": 120,
      "purchases": 0,
      "cac": 0,
      "atc": 0,
      "atc_abandon_rate": 0,
      "frequency": 1.35,
      "age": "18\u201365",
      "gender": "All"
    },
    {
      "id": "120243750635620161",
      "name": "Bangalore+Mumbai | UGC | Batch 05",
      "status": "ACTIVE",
      "daily_budget": 800.0,
      "spend": 5078.41,
      "impressions": 17986,
      "link_clicks": 454,
      "purchases": 11,
      "cac": 461.67,
      "atc": 64,
      "atc_abandon_rate": 82.8,
      "frequency": 1.27,
      "age": "18\u201365",
      "gender": "All"
    },
    {
      "id": "120243630880490161",
      "name": "Ahmedabad | UGC | Batch 3 - Only AHM",
      "status": "PAUSED",
      "daily_budget": 2000.0,
      "spend": 5306.44,
      "impressions": 51145,
      "link_clicks": 419,
      "purchases": 3,
      "cac": 1768.81,
      "atc": 4,
      "atc_abandon_rate": 25.0,
      "frequency": 1.54,
      "age": "18\u201365",
      "gender": "All"
    },
    {
      "id": "120243563203840161",
      "name": "Open AUD | Sugar Combo | 25/3/2026",
      "status": "ACTIVE",
      "daily_budget": 800.0,
      "spend": 6839.29,
      "impressions": 24009,
      "link_clicks": 179,
      "purchases": 7,
      "cac": 977.04,
      "atc": 37,
      "atc_abandon_rate": 81.1,
      "frequency": 1.87,
      "age": "18\u201365",
      "gender": "All"
    },
    {
      "id": "120243562429440161",
      "name": "Open AUD | Mascot Batch | 25/3/2026",
      "status": "PAUSED",
      "daily_budget": 800.0,
      "spend": 4038.26,
      "impressions": 14312,
      "link_clicks": 109,
      "purchases": 2,
      "cac": 2019.13,
      "atc": 22,
      "atc_abandon_rate": 90.9,
      "frequency": 1.55,
      "age": "18\u201365",
      "gender": "All"
    },
    {
      "id": "120243553089990161",
      "name": "Open AUD | Static CT | Holo-WR | 250326",
      "status": "ACTIVE",
      "daily_budget": 1000.0,
      "spend": 9729.54,
      "impressions": 36574,
      "link_clicks": 458,
      "purchases": 14,
      "cac": 694.97,
      "atc": 99,
      "atc_abandon_rate": 85.9,
      "frequency": 2.12,
      "age": "18\u201365",
      "gender": "All"
    },
    {
      "id": "120243432146500161",
      "name": "TV_WEL_KNJ+VINEGAR_WINNERCT_25-65+_OpenAUD",
      "status": "ACTIVE",
      "daily_budget": 0.0,
      "spend": 14943.74,
      "impressions": 24835,
      "link_clicks": 442,
      "purchases": 20,
      "cac": 747.19,
      "atc": 128,
      "atc_abandon_rate": 84.4,
      "frequency": 1.23,
      "age": "18\u201365",
      "gender": "All"
    },
    {
      "id": "120243187617510161",
      "name": "TV-NUT-VID02-IG",
      "status": "PAUSED",
      "daily_budget": 1500.0,
      "spend": 0.0,
      "impressions": 0,
      "link_clicks": 0,
      "purchases": 0,
      "cac": 0,
      "atc": 0,
      "atc_abandon_rate": 0,
      "frequency": 0.0,
      "age": "18\u201365",
      "gender": "All"
    },
    {
      "id": "120243185559380161",
      "name": "Small_BusinessOwner_MUM",
      "status": "PAUSED",
      "daily_budget": 1000.0,
      "spend": 3132.19,
      "impressions": 51766,
      "link_clicks": 631,
      "purchases": 0,
      "cac": 0,
      "atc": 0,
      "atc_abandon_rate": 0,
      "frequency": 1.46,
      "age": "18\u201365",
      "gender": "All"
    },
    {
      "id": "120243185548830161",
      "name": "Small_BusinessOwner_GJ",
      "status": "ACTIVE",
      "daily_budget": 1000.0,
      "spend": 16874.23,
      "impressions": 703474,
      "link_clicks": 3332,
      "purchases": 1,
      "cac": 16874.23,
      "atc": 3,
      "atc_abandon_rate": 66.7,
      "frequency": 1.31,
      "age": "18\u201365",
      "gender": "All"
    },
    {
      "id": "120243156193000161",
      "name": "GUJ_VD_Batch1_170326",
      "status": "ACTIVE",
      "daily_budget": 1000.0,
      "spend": 16380.28,
      "impressions": 174486,
      "link_clicks": 1519,
      "purchases": 30,
      "cac": 546.01,
      "atc": 186,
      "atc_abandon_rate": 83.9,
      "frequency": 1.47,
      "age": "18\u201365",
      "gender": "All"
    },
    {
      "id": "120243148973340161",
      "name": "AHD+MUM+BLG | UGC | Batch 4",
      "status": "PAUSED",
      "daily_budget": 1500.0,
      "spend": 5863.77,
      "impressions": 13686,
      "link_clicks": 324,
      "purchases": 6,
      "cac": 977.3,
      "atc": 17,
      "atc_abandon_rate": 64.7,
      "frequency": 1.45,
      "age": "18\u201365",
      "gender": "All"
    },
    {
      "id": "120243131623420161",
      "name": "Small_BusinessOwner_RJ",
      "status": "ACTIVE",
      "daily_budget": 1000.0,
      "spend": 13665.95,
      "impressions": 834667,
      "link_clicks": 2729,
      "purchases": 0,
      "cac": 0,
      "atc": 0,
      "atc_abandon_rate": 0,
      "frequency": 1.21,
      "age": "18\u201365",
      "gender": "All"
    },
    {
      "id": "120243077747840161",
      "name": "TV_Jam_VD1_OpenAUD",
      "status": "ACTIVE",
      "daily_budget": 3000.0,
      "spend": 48368.88,
      "impressions": 165753,
      "link_clicks": 3503,
      "purchases": 66,
      "cac": 732.86,
      "atc": 447,
      "atc_abandon_rate": 85.2,
      "frequency": 1.8,
      "age": "18\u201365",
      "gender": "All"
    },
    {
      "id": "120242938232130161",
      "name": "Ahmedabad | UGC | Batch 3",
      "status": "PAUSED",
      "daily_budget": 3000.0,
      "spend": 50299.91,
      "impressions": 544152,
      "link_clicks": 6666,
      "purchases": 38,
      "cac": 1323.68,
      "atc": 184,
      "atc_abandon_rate": 79.3,
      "frequency": 2.26,
      "age": "18\u201365",
      "gender": "All"
    },
    {
      "id": "120242938202650161",
      "name": "Ahmedabad | UGC | Batch 02",
      "status": "PAUSED",
      "daily_budget": 3000.0,
      "spend": 6603.82,
      "impressions": 38123,
      "link_clicks": 569,
      "purchases": 4,
      "cac": 1650.95,
      "atc": 24,
      "atc_abandon_rate": 83.3,
      "frequency": 1.72,
      "age": "18\u201365",
      "gender": "All"
    }
  ],
  "ads": [
    {
      "id": "120244145495780161",
      "name": "TV_FRO_VID03",
      "status": "ACTIVE",
      "adset": "120244145495790161",
      "spend": 0.0,
      "impressions": 0,
      "link_clicks": 0,
      "ctr": 0.0,
      "purchases": 0,
      "cac": 0,
      "atc": 0,
      "frequency": 0.0,
      "hook_rate": 0,
      "thumb_stop_rate": 0,
      "revenue": 0.0,
      "roas": 0
    },
    {
      "id": "120244145495800161",
      "name": "TV_FRO_VID02",
      "status": "ACTIVE",
      "adset": "120244145495790161",
      "spend": 0.0,
      "impressions": 0,
      "link_clicks": 0,
      "ctr": 0.0,
      "purchases": 0,
      "cac": 0,
      "atc": 0,
      "frequency": 0.0,
      "hook_rate": 0,
      "thumb_stop_rate": 0,
      "revenue": 0.0,
      "roas": 0
    },
    {
      "id": "120244145495810161",
      "name": "TV_FRO_VID01",
      "status": "ACTIVE",
      "adset": "120244145495790161",
      "spend": 0.0,
      "impressions": 0,
      "link_clicks": 0,
      "ctr": 0.0,
      "purchases": 0,
      "cac": 0,
      "atc": 0,
      "frequency": 0.0,
      "hook_rate": 0,
      "thumb_stop_rate": 0,
      "revenue": 0.0,
      "roas": 0
    },
    {
      "id": "120244074259340161",
      "name": "TV_FRO_VID03",
      "status": "ACTIVE",
      "adset": "120244073473760161",
      "spend": 290.95,
      "impressions": 1208,
      "link_clicks": 43,
      "ctr": 3.73,
      "purchases": 4,
      "cac": 72.74,
      "atc": 19,
      "frequency": 1.03,
      "hook_rate": 50.41,
      "thumb_stop_rate": 3.56,
      "revenue": 4410.0,
      "roas": 15.16
    },
    {
      "id": "120244073815010161",
      "name": "TV_FRO_VID02",
      "status": "ACTIVE",
      "adset": "120244073473760161",
      "spend": 8.67,
      "impressions": 33,
      "link_clicks": 0,
      "ctr": 0.0,
      "purchases": 0,
      "cac": 0,
      "atc": 0,
      "frequency": 1.0,
      "hook_rate": 12.12,
      "thumb_stop_rate": 0.0,
      "revenue": 0.0,
      "roas": 0.0
    },
    {
      "id": "120244073473770161",
      "name": "TV_FRO_VID01",
      "status": "ACTIVE",
      "adset": "120244073473760161",
      "spend": 167.88,
      "impressions": 680,
      "link_clicks": 9,
      "ctr": 1.47,
      "purchases": 0,
      "cac": 0,
      "atc": 0,
      "frequency": 1.02,
      "hook_rate": 42.94,
      "thumb_stop_rate": 1.32,
      "revenue": 0.0,
      "roas": 0.0
    },
    {
      "id": "120243993730650161",
      "name": "Amazon LP | Video 1 | C8 - 1st hook | Jamun Strips",
      "status": "ACTIVE",
      "adset": "120243993730680161",
      "spend": 62.4,
      "impressions": 251,
      "link_clicks": 4,
      "ctr": 2.79,
      "purchases": 0,
      "cac": 0,
      "atc": 0,
      "frequency": 1.19,
      "hook_rate": 17.13,
      "thumb_stop_rate": 1.59,
      "revenue": 0.0,
      "roas": 0.0
    },
    {
      "id": "120243993730660161",
      "name": "Amazon LP | C3 - 2nd hook | Jamun Strip +  Jamun Cube Combo",
      "status": "ACTIVE",
      "adset": "120243993730690161",
      "spend": 288.02,
      "impressions": 1395,
      "link_clicks": 25,
      "ctr": 2.01,
      "purchases": 0,
      "cac": 0,
      "atc": 2,
      "frequency": 1.15,
      "hook_rate": 18.21,
      "thumb_stop_rate": 1.79,
      "revenue": 0.0,
      "roas": 0.0
    },
    {
      "id": "120243993730670161",
      "name": "Amazon LP | C3 - 1st hook | Jamun Strip +  Jamun Cube Combo",
      "status": "ACTIVE",
      "adset": "120243993730690161",
      "spend": 48.62,
      "impressions": 162,
      "link_clicks": 6,
      "ctr": 3.7,
      "purchases": 0,
      "cac": 0,
      "atc": 0,
      "frequency": 1.17,
      "hook_rate": 22.84,
      "thumb_stop_rate": 3.7,
      "revenue": 0.0,
      "roas": 0.0
    },
    {
      "id": "120243993730700161",
      "name": "Amazon LP | C3 - 3rd hook | Jamun Strip +  Jamun Cube Combo",
      "status": "ACTIVE",
      "adset": "120243993730690161",
      "spend": 316.95,
      "impressions": 2370,
      "link_clicks": 14,
      "ctr": 1.05,
      "purchases": 1,
      "cac": 316.95,
      "atc": 4,
      "frequency": 1.19,
      "hook_rate": 24.43,
      "thumb_stop_rate": 0.59,
      "revenue": 630.0,
      "roas": 1.99
    },
    {
      "id": "120242632095530161",
      "name": "Image 2",
      "status": "PAUSED",
      "adset": "120242630920570161",
      "spend": 38311.71,
      "impressions": 185144,
      "link_clicks": 2214,
      "ctr": 1.3,
      "purchases": 69,
      "cac": 555.24,
      "atc": 423,
      "frequency": 2.44,
      "hook_rate": 0.05,
      "thumb_stop_rate": 1.2,
      "revenue": 89359.07,
      "roas": 2.33
    },
    {
      "id": "120243750635630161",
      "name": "TV-FRO-VID01",
      "status": "ACTIVE",
      "adset": "120243750635620161",
      "spend": 5078.41,
      "impressions": 17986,
      "link_clicks": 454,
      "ctr": 3.16,
      "purchases": 11,
      "cac": 461.67,
      "atc": 64,
      "frequency": 1.27,
      "hook_rate": 42.87,
      "thumb_stop_rate": 2.52,
      "revenue": 10722.0,
      "roas": 2.11
    },
    {
      "id": "120243754651980161",
      "name": "TV-FRO-VID01",
      "status": "ACTIVE",
      "adset": "120243754651990161",
      "spend": 1240.67,
      "impressions": 6658,
      "link_clicks": 120,
      "ctr": 3.12,
      "purchases": 0,
      "cac": 0,
      "atc": 0,
      "frequency": 1.35,
      "hook_rate": 41.21,
      "thumb_stop_rate": 1.8,
      "revenue": 0.0,
      "roas": 0.0
    },
    {
      "id": "120242628456800161",
      "name": "Video 2 | Brand Booth",
      "status": "PAUSED",
      "adset": "120242624867100161",
      "spend": 8228.14,
      "impressions": 34379,
      "link_clicks": 575,
      "ctr": 2.38,
      "purchases": 12,
      "cac": 685.68,
      "atc": 73,
      "frequency": 1.63,
      "hook_rate": 36.54,
      "thumb_stop_rate": 1.67,
      "revenue": 9029.0,
      "roas": 1.1
    },
    {
      "id": "120242624867090161",
      "name": "Video 1 | Strip-Jam",
      "status": "PAUSED",
      "adset": "120242624867100161",
      "spend": 48635.47,
      "impressions": 541504,
      "link_clicks": 3638,
      "ctr": 0.99,
      "purchases": 97,
      "cac": 501.4,
      "atc": 547,
      "frequency": 1.74,
      "hook_rate": 26.4,
      "thumb_stop_rate": 0.67,
      "revenue": 82542.0,
      "roas": 1.7
    },
    {
      "id": "120243630880510161",
      "name": "TV-FRO-VID03-VAR03",
      "status": "ACTIVE",
      "adset": "120243630880490161",
      "spend": 210.94,
      "impressions": 1589,
      "link_clicks": 17,
      "ctr": 1.26,
      "purchases": 0,
      "cac": 0,
      "atc": 0,
      "frequency": 1.23,
      "hook_rate": 10.2,
      "thumb_stop_rate": 1.07,
      "revenue": 0.0,
      "roas": 0.0
    },
    {
      "id": "120243630880470161",
      "name": "TV-FRO-VID04",
      "status": "ACTIVE",
      "adset": "120243630880490161",
      "spend": 769.87,
      "impressions": 5640,
      "link_clicks": 32,
      "ctr": 0.82,
      "purchases": 0,
      "cac": 0,
      "atc": 2,
      "frequency": 1.44,
      "hook_rate": 25.51,
      "thumb_stop_rate": 0.57,
      "revenue": 0.0,
      "roas": 0.0
    },
    {
      "id": "120243630880460161",
      "name": "TV-FRO-VID03-VAR01",
      "status": "ACTIVE",
      "adset": "120243630880490161",
      "spend": 1264.54,
      "impressions": 10827,
      "link_clicks": 89,
      "ctr": 1.2,
      "purchases": 1,
      "cac": 1264.54,
      "atc": 2,
      "frequency": 1.33,
      "hook_rate": 13.08,
      "thumb_stop_rate": 0.82,
      "revenue": 660.0,
      "roas": 0.52
    },
    {
      "id": "120243630880520161",
      "name": "TV-FRO-VID06",
      "status": "PAUSED",
      "adset": "120243630880490161",
      "spend": 0.0,
      "impressions": 0,
      "link_clicks": 0,
      "ctr": 0.0,
      "purchases": 0,
      "cac": 0,
      "atc": 0,
      "frequency": 0.0,
      "hook_rate": 0,
      "thumb_stop_rate": 0,
      "revenue": 0.0,
      "roas": 0
    },
    {
      "id": "120243630880500161",
      "name": "TV-FRO-VID05",
      "status": "ACTIVE",
      "adset": "120243630880490161",
      "spend": 3061.09,
      "impressions": 33089,
      "link_clicks": 281,
      "ctr": 1.2,
      "purchases": 2,
      "cac": 1530.55,
      "atc": 0,
      "frequency": 1.24,
      "hook_rate": 33.7,
      "thumb_stop_rate": 0.85,
      "revenue": 2516.0,
      "roas": 0.82
    },
    {
      "id": "120243630880480161",
      "name": "TV-FRO-VID03-VAR02",
      "status": "PAUSED",
      "adset": "120243630880490161",
      "spend": 0.0,
      "impressions": 0,
      "link_clicks": 0,
      "ctr": 0.0,
      "purchases": 0,
      "cac": 0,
      "atc": 0,
      "frequency": 0.0,
      "hook_rate": 0,
      "thumb_stop_rate": 0,
      "revenue": 0.0,
      "roas": 0
    },
    {
      "id": "120239047650790161",
      "name": "Image 3",
      "status": "PAUSED",
      "adset": "120239047604380161",
      "spend": 56291.01,
      "impressions": 285610,
      "link_clicks": 2490,
      "ctr": 1.09,
      "purchases": 100,
      "cac": 562.91,
      "atc": 482,
      "frequency": 1.98,
      "hook_rate": 0.0,
      "thumb_stop_rate": 0.87,
      "revenue": 93046.0,
      "roas": 1.65
    },
    {
      "id": "120243563203850161",
      "name": "Image 4",
      "status": "ACTIVE",
      "adset": "120243563203840161",
      "spend": 4369.58,
      "impressions": 16350,
      "link_clicks": 120,
      "ctr": 1.0,
      "purchases": 4,
      "cac": 1092.39,
      "atc": 21,
      "frequency": 1.6,
      "hook_rate": 0.0,
      "thumb_stop_rate": 0.73,
      "revenue": 3797.0,
      "roas": 0.87
    },
    {
      "id": "120243563203860161",
      "name": "Image 2",
      "status": "ACTIVE",
      "adset": "120243563203840161",
      "spend": 560.0,
      "impressions": 2026,
      "link_clicks": 16,
      "ctr": 0.94,
      "purchases": 0,
      "cac": 0,
      "atc": 0,
      "frequency": 1.49,
      "hook_rate": 0.0,
      "thumb_stop_rate": 0.79,
      "revenue": 0.0,
      "roas": 0.0
    },
    {
      "id": "120243563203830161",
      "name": "Image 1",
      "status": "ACTIVE",
      "adset": "120243563203840161",
      "spend": 967.2,
      "impressions": 2558,
      "link_clicks": 23,
      "ctr": 1.09,
      "purchases": 1,
      "cac": 967.2,
      "atc": 10,
      "frequency": 1.46,
      "hook_rate": 0.0,
      "thumb_stop_rate": 0.9,
      "revenue": 1381.0,
      "roas": 1.43
    },
    {
      "id": "120243563100580161",
      "name": "Image 2",
      "status": "ACTIVE",
      "adset": "120243562429440161",
      "spend": 160.5,
      "impressions": 461,
      "link_clicks": 2,
      "ctr": 0.43,
      "purchases": 0,
      "cac": 0,
      "atc": 0,
      "frequency": 1.13,
      "hook_rate": 0.0,
      "thumb_stop_rate": 0.43,
      "revenue": 0.0,
      "roas": 0.0
    },
    {
      "id": "120243563100570161",
      "name": "Image 4",
      "status": "ACTIVE",
      "adset": "120243562429440161",
      "spend": 691.25,
      "impressions": 2608,
      "link_clicks": 21,
      "ctr": 1.07,
      "purchases": 1,
      "cac": 691.25,
      "atc": 4,
      "frequency": 1.35,
      "hook_rate": 0.0,
      "thumb_stop_rate": 0.81,
      "revenue": 2205.0,
      "roas": 3.19
    },
    {
      "id": "120243562429420161",
      "name": "Image 1",
      "status": "ACTIVE",
      "adset": "120243562429440161",
      "spend": 648.68,
      "impressions": 2089,
      "link_clicks": 15,
      "ctr": 0.86,
      "purchases": 0,
      "cac": 0,
      "atc": 3,
      "frequency": 1.26,
      "hook_rate": 0.0,
      "thumb_stop_rate": 0.72,
      "revenue": 0.0,
      "roas": 0.0
    },
    {
      "id": "120243563203870161",
      "name": "Image 3",
      "status": "ACTIVE",
      "adset": "120243563203840161",
      "spend": 942.51,
      "impressions": 3075,
      "link_clicks": 20,
      "ctr": 0.81,
      "purchases": 2,
      "cac": 471.25,
      "atc": 6,
      "frequency": 1.4,
      "hook_rate": 0.0,
      "thumb_stop_rate": 0.65,
      "revenue": 1599.0,
      "roas": 1.7
    },
    {
      "id": "120243563100560161",
      "name": "Image 3",
      "status": "ACTIVE",
      "adset": "120243562429440161",
      "spend": 2537.83,
      "impressions": 9154,
      "link_clicks": 71,
      "ctr": 0.99,
      "purchases": 1,
      "cac": 2537.83,
      "atc": 15,
      "frequency": 1.36,
      "hook_rate": 0.0,
      "thumb_stop_rate": 0.78,
      "revenue": 569.0,
      "roas": 0.22
    }
  ],
  "spendTrend": [
    {
      "day": "03-06",
      "spend": 32296.85,
      "impressions": 444952,
      "link_clicks": 1919,
      "purchases": 81,
      "revenue": 68604.2,
      "cac": 398.73,
      "roas": 2.12
    },
    {
      "day": "03-07",
      "spend": 32940.1,
      "impressions": 447484,
      "link_clicks": 2114,
      "purchases": 70,
      "revenue": 63740.4,
      "cac": 470.57,
      "roas": 1.94
    },
    {
      "day": "03-08",
      "spend": 41602.73,
      "impressions": 483628,
      "link_clicks": 2566,
      "purchases": 69,
      "revenue": 64453.6,
      "cac": 602.94,
      "roas": 1.55
    },
    {
      "day": "03-09",
      "spend": 43173.26,
      "impressions": 513844,
      "link_clicks": 2826,
      "purchases": 81,
      "revenue": 71534.2,
      "cac": 533.0,
      "roas": 1.66
    },
    {
      "day": "03-10",
      "spend": 43888.64,
      "impressions": 494142,
      "link_clicks": 3087,
      "purchases": 68,
      "revenue": 55566.0,
      "cac": 645.42,
      "roas": 1.27
    },
    {
      "day": "03-11",
      "spend": 42826.0,
      "impressions": 472071,
      "link_clicks": 2918,
      "purchases": 60,
      "revenue": 61344.2,
      "cac": 713.77,
      "roas": 1.43
    },
    {
      "day": "03-12",
      "spend": 65541.52,
      "impressions": 566495,
      "link_clicks": 4669,
      "purchases": 109,
      "revenue": 108127.89,
      "cac": 601.3,
      "roas": 1.65
    },
    {
      "day": "03-13",
      "spend": 73466.17,
      "impressions": 566843,
      "link_clicks": 4660,
      "purchases": 95,
      "revenue": 78259.2,
      "cac": 773.33,
      "roas": 1.07
    },
    {
      "day": "03-14",
      "spend": 76317.93,
      "impressions": 574174,
      "link_clicks": 4591,
      "purchases": 126,
      "revenue": 117847.64,
      "cac": 605.7,
      "roas": 1.54
    },
    {
      "day": "03-15",
      "spend": 94591.77,
      "impressions": 702124,
      "link_clicks": 6293,
      "purchases": 162,
      "revenue": 159682.05,
      "cac": 583.9,
      "roas": 1.69
    },
    {
      "day": "03-16",
      "spend": 91580.84,
      "impressions": 728365,
      "link_clicks": 6411,
      "purchases": 176,
      "revenue": 166761.36,
      "cac": 520.35,
      "roas": 1.82
    },
    {
      "day": "03-17",
      "spend": 91351.3,
      "impressions": 700149,
      "link_clicks": 6048,
      "purchases": 108,
      "revenue": 95575.0,
      "cac": 845.85,
      "roas": 1.05
    },
    {
      "day": "03-18",
      "spend": 95748.99,
      "impressions": 709198,
      "link_clicks": 5903,
      "purchases": 116,
      "revenue": 110288.0,
      "cac": 825.42,
      "roas": 1.15
    },
    {
      "day": "03-19",
      "spend": 98873.53,
      "impressions": 753944,
      "link_clicks": 6949,
      "purchases": 125,
      "revenue": 117317.25,
      "cac": 790.99,
      "roas": 1.19
    },
    {
      "day": "03-20",
      "spend": 96141.24,
      "impressions": 729298,
      "link_clicks": 6497,
      "purchases": 131,
      "revenue": 132114.53,
      "cac": 733.9,
      "roas": 1.37
    },
    {
      "day": "03-21",
      "spend": 88458.91,
      "impressions": 721299,
      "link_clicks": 6514,
      "purchases": 153,
      "revenue": 139890.0,
      "cac": 578.16,
      "roas": 1.58
    },
    {
      "day": "03-22",
      "spend": 100364.05,
      "impressions": 778033,
      "link_clicks": 6820,
      "purchases": 131,
      "revenue": 104597.0,
      "cac": 766.14,
      "roas": 1.04
    },
    {
      "day": "03-23",
      "spend": 90929.68,
      "impressions": 665290,
      "link_clicks": 5953,
      "purchases": 125,
      "revenue": 105376.6,
      "cac": 727.44,
      "roas": 1.16
    },
    {
      "day": "03-24",
      "spend": 90298.28,
      "impressions": 1560485,
      "link_clicks": 7273,
      "purchases": 102,
      "revenue": 78394.0,
      "cac": 885.28,
      "roas": 0.87
    },
    {
      "day": "03-25",
      "spend": 91843.89,
      "impressions": 761104,
      "link_clicks": 5911,
      "purchases": 126,
      "revenue": 105560.6,
      "cac": 728.92,
      "roas": 1.15
    },
    {
      "day": "03-26",
      "spend": 85137.01,
      "impressions": 681490,
      "link_clicks": 5157,
      "purchases": 118,
      "revenue": 114995.19,
      "cac": 721.5,
      "roas": 1.35
    },
    {
      "day": "03-27",
      "spend": 78393.15,
      "impressions": 602925,
      "link_clicks": 4623,
      "purchases": 126,
      "revenue": 119897.74,
      "cac": 622.17,
      "roas": 1.53
    },
    {
      "day": "03-28",
      "spend": 71990.19,
      "impressions": 576757,
      "link_clicks": 4558,
      "purchases": 96,
      "revenue": 87231.0,
      "cac": 749.9,
      "roas": 1.21
    },
    {
      "day": "03-29",
      "spend": 83935.81,
      "impressions": 648043,
      "link_clicks": 5700,
      "purchases": 126,
      "revenue": 109988.04,
      "cac": 666.16,
      "roas": 1.31
    },
    {
      "day": "03-30",
      "spend": 78670.81,
      "impressions": 574473,
      "link_clicks": 4916,
      "purchases": 127,
      "revenue": 117438.2,
      "cac": 619.46,
      "roas": 1.49
    },
    {
      "day": "03-31",
      "spend": 76930.8,
      "impressions": 562986,
      "link_clicks": 5508,
      "purchases": 126,
      "revenue": 113786.24,
      "cac": 610.56,
      "roas": 1.48
    },
    {
      "day": "04-01",
      "spend": 73250.38,
      "impressions": 587300,
      "link_clicks": 5212,
      "purchases": 128,
      "revenue": 105632.2,
      "cac": 572.27,
      "roas": 1.44
    },
    {
      "day": "04-02",
      "spend": 73543.4,
      "impressions": 565888,
      "link_clicks": 4809,
      "purchases": 131,
      "revenue": 115943.08,
      "cac": 561.4,
      "roas": 1.58
    }
  ],
  "audienceAge": [
    {
      "group": "18-24",
      "reach": 3414595,
      "clicks": 8632,
      "spend": 52752.13,
      "purchases": 43,
      "revenue": 46893.0,
      "frequency": 4.34,
      "count": 3,
      "cac": 1226.79,
      "roas": 0.89,
      "avg_frequency": 1.45
    },
    {
      "group": "25-34",
      "reach": 2000238,
      "clicks": 33537,
      "spend": 308896.72,
      "purchases": 446,
      "revenue": 401578.52,
      "frequency": 6.44,
      "count": 3,
      "cac": 692.59,
      "roas": 1.3,
      "avg_frequency": 2.15
    },
    {
      "group": "35-44",
      "reach": 1220725,
      "clicks": 48943,
      "spend": 568230.87,
      "purchases": 885,
      "revenue": 815000.3200000001,
      "frequency": 9.12,
      "count": 3,
      "cac": 642.07,
      "roas": 1.43,
      "avg_frequency": 3.04
    },
    {
      "group": "45-54",
      "reach": 684348,
      "clicks": 42935,
      "spend": 567932.3599999999,
      "purchases": 872,
      "revenue": 775787.55,
      "frequency": 11.23,
      "count": 3,
      "cac": 651.3,
      "roas": 1.37,
      "avg_frequency": 3.74
    },
    {
      "group": "55-64",
      "reach": 329121,
      "clicks": 35231,
      "spend": 400077.62,
      "purchases": 608,
      "revenue": 540901.77,
      "frequency": 13.07,
      "count": 3,
      "cac": 658.02,
      "roas": 1.35,
      "avg_frequency": 4.36
    },
    {
      "group": "65+",
      "reach": 177833,
      "clicks": 21823,
      "spend": 205313.09,
      "purchases": 337,
      "revenue": 309154.23,
      "frequency": 11.85,
      "count": 3,
      "cac": 609.24,
      "roas": 1.51,
      "avg_frequency": 3.95
    },
    {
      "group": "Unknown",
      "reach": 880,
      "clicks": 2951,
      "spend": 884.44,
      "purchases": 1,
      "revenue": 630.0,
      "frequency": 887348.04,
      "count": 3,
      "cac": 884.44,
      "roas": 0.71,
      "avg_frequency": 295782.68
    }
  ],
  "audienceGender": {
    "male": 75,
    "female": 25
  },
  "geography": [
    {
      "region": "Andhra Pradesh",
      "reach": 33033,
      "clicks": 1908,
      "impressions": 114281,
      "spend": 24170.58,
      "purchases": 0,
      "revenue": 2879.0,
      "shopify_orders": 4,
      "revenue_source": "shopify",
      "cac": 0,
      "roas": 0.12,
      "ctr": 1.67
    },
    {
      "region": "Chhattisgarh",
      "reach": 20753,
      "clicks": 1413,
      "impressions": 97173,
      "spend": 20698.68,
      "purchases": 0,
      "revenue": 630.0,
      "shopify_orders": 1,
      "revenue_source": "shopify",
      "cac": 0,
      "roas": 0.03,
      "ctr": 1.45
    },
    {
      "region": "Chandigarh",
      "reach": 7292,
      "clicks": 495,
      "impressions": 32066,
      "spend": 9945.82,
      "purchases": 0,
      "revenue": 0.0,
      "shopify_orders": 0,
      "revenue_source": "meta_pixel",
      "cac": 0,
      "roas": 0.0,
      "ctr": 1.54
    },
    {
      "region": "Andaman and Nicobar Islands",
      "reach": 2061,
      "clicks": 204,
      "impressions": 11130,
      "spend": 3264.16,
      "purchases": 0,
      "revenue": 0.0,
      "shopify_orders": 0,
      "revenue_source": "meta_pixel",
      "cac": 0,
      "roas": 0.0,
      "ctr": 1.83
    },
    {
      "region": "California",
      "reach": 10,
      "clicks": 3,
      "impressions": 98,
      "spend": 28.95,
      "purchases": 0,
      "revenue": 0.0,
      "shopify_orders": 0,
      "revenue_source": "meta_pixel",
      "cac": 0,
      "roas": 0.0,
      "ctr": 3.06
    },
    {
      "region": "Ahmadi Governorate",
      "reach": 2,
      "clicks": 1,
      "impressions": 38,
      "spend": 9.81,
      "purchases": 0,
      "revenue": 0.0,
      "shopify_orders": 0,
      "revenue_source": "meta_pixel",
      "cac": 0,
      "roas": 0.0,
      "ctr": 2.63
    },
    {
      "region": "Capital Governorate",
      "reach": 2,
      "clicks": 1,
      "impressions": 8,
      "spend": 1.9,
      "purchases": 0,
      "revenue": 0.0,
      "shopify_orders": 0,
      "revenue_source": "meta_pixel",
      "cac": 0,
      "roas": 0.0,
      "ctr": 12.5
    },
    {
      "region": "Bayern",
      "reach": 3,
      "clicks": 0,
      "impressions": 6,
      "spend": 1.41,
      "purchases": 0,
      "revenue": 0.0,
      "shopify_orders": 0,
      "revenue_source": "meta_pixel",
      "cac": 0,
      "roas": 0.0,
      "ctr": 0.0
    },
    {
      "region": "Bangkok",
      "reach": 6,
      "clicks": 0,
      "impressions": 7,
      "spend": 0.98,
      "purchases": 0,
      "revenue": 0.0,
      "shopify_orders": 0,
      "revenue_source": "meta_pixel",
      "cac": 0,
      "roas": 0.0,
      "ctr": 0.0
    },
    {
      "region": "British Columbia",
      "reach": 5,
      "clicks": 0,
      "impressions": 8,
      "spend": 0.91,
      "purchases": 0,
      "revenue": 0.0,
      "shopify_orders": 0,
      "revenue_source": "meta_pixel",
      "cac": 0,
      "roas": 0.0,
      "ctr": 0.0
    },
    {
      "region": "Arizona",
      "reach": 2,
      "clicks": 0,
      "impressions": 4,
      "spend": 0.49,
      "purchases": 0,
      "revenue": 0.0,
      "shopify_orders": 0,
      "revenue_source": "meta_pixel",
      "cac": 0,
      "roas": 0.0,
      "ctr": 0.0
    },
    {
      "region": "Abu Dhabi",
      "reach": 4,
      "clicks": 0,
      "impressions": 7,
      "spend": 0.31,
      "purchases": 0,
      "revenue": 0.0,
      "shopify_orders": 0,
      "revenue_source": "meta_pixel",
      "cac": 0,
      "roas": 0.0,
      "ctr": 0.0
    },
    {
      "region": "Bali",
      "reach": 2,
      "clicks": 0,
      "impressions": 2,
      "spend": 0.18,
      "purchases": 0,
      "revenue": 0.0,
      "shopify_orders": 0,
      "revenue_source": "meta_pixel",
      "cac": 0,
      "roas": 0.0,
      "ctr": 0.0
    },
    {
      "region": "Berlin",
      "reach": 3,
      "clicks": 0,
      "impressions": 4,
      "spend": 0.16,
      "purchases": 0,
      "revenue": 0.0,
      "shopify_orders": 0,
      "revenue_source": "meta_pixel",
      "cac": 0,
      "roas": 0.0,
      "ctr": 0.0
    },
    {
      "region": "Ad Dakhiliyah Governorate",
      "reach": 2,
      "clicks": 0,
      "impressions": 3,
      "spend": 0.15,
      "purchases": 0,
      "revenue": 0.0,
      "shopify_orders": 0,
      "revenue_source": "meta_pixel",
      "cac": 0,
      "roas": 0.0,
      "ctr": 0.0
    },
    {
      "region": "Arauca",
      "reach": 1,
      "clicks": 0,
      "impressions": 1,
      "spend": 0.13,
      "purchases": 0,
      "revenue": 0.0,
      "shopify_orders": 0,
      "revenue_source": "meta_pixel",
      "cac": 0,
      "roas": 0.0,
      "ctr": 0.0
    },
    {
      "region": "Chiang Rai",
      "reach": 1,
      "clicks": 0,
      "impressions": 1,
      "spend": 0.12,
      "purchases": 0,
      "revenue": 0.0,
      "shopify_orders": 0,
      "revenue_source": "meta_pixel",
      "cac": 0,
      "roas": 0.0,
      "ctr": 0.0
    },
    {
      "region": "Baja California",
      "reach": 1,
      "clicks": 0,
      "impressions": 1,
      "spend": 0.08,
      "purchases": 0,
      "revenue": 0.0,
      "shopify_orders": 0,
      "revenue_source": "meta_pixel",
      "cac": 0,
      "roas": 0.0,
      "ctr": 0.0
    },
    {
      "region": "Brussels",
      "reach": 1,
      "clicks": 0,
      "impressions": 2,
      "spend": 0.07,
      "purchases": 0,
      "revenue": 0.0,
      "shopify_orders": 0,
      "revenue_source": "meta_pixel",
      "cac": 0,
      "roas": 0.0,
      "ctr": 0.0
    },
    {
      "region": "Chihuahua",
      "reach": 1,
      "clicks": 0,
      "impressions": 1,
      "spend": 0.07,
      "purchases": 0,
      "revenue": 0.0,
      "shopify_orders": 0,
      "revenue_source": "meta_pixel",
      "cac": 0,
      "roas": 0.0,
      "ctr": 0.0
    },
    {
      "region": "Al Madinah Region",
      "reach": 4,
      "clicks": 0,
      "impressions": 7,
      "spend": 0.05,
      "purchases": 0,
      "revenue": 0.0,
      "shopify_orders": 0,
      "revenue_source": "meta_pixel",
      "cac": 0,
      "roas": 0.0,
      "ctr": 0.0
    },
    {
      "region": "Alberta",
      "reach": 3,
      "clicks": 0,
      "impressions": 3,
      "spend": 0.05,
      "purchases": 0,
      "revenue": 0.0,
      "shopify_orders": 0,
      "revenue_source": "meta_pixel",
      "cac": 0,
      "roas": 0.0,
      "ctr": 0.0
    },
    {
      "region": "Bheri Zone",
      "reach": 1,
      "clicks": 0,
      "impressions": 1,
      "spend": 0.05,
      "purchases": 0,
      "revenue": 0.0,
      "shopify_orders": 0,
      "revenue_source": "meta_pixel",
      "cac": 0,
      "roas": 0.0,
      "ctr": 0.0
    },
    {
      "region": "Bucharest",
      "reach": 1,
      "clicks": 0,
      "impressions": 1,
      "spend": 0.04,
      "purchases": 0,
      "revenue": 0.0,
      "shopify_orders": 0,
      "revenue_source": "meta_pixel",
      "cac": 0,
      "roas": 0.0,
      "ctr": 0.0
    },
    {
      "region": "Andalusia",
      "reach": 1,
      "clicks": 0,
      "impressions": 1,
      "spend": 0.03,
      "purchases": 0,
      "revenue": 0.0,
      "shopify_orders": 0,
      "revenue_source": "meta_pixel",
      "cac": 0,
      "roas": 0.0,
      "ctr": 0.0
    },
    {
      "region": "Baden-W\u00fcrttemberg",
      "reach": 1,
      "clicks": 0,
      "impressions": 1,
      "spend": 0.03,
      "purchases": 0,
      "revenue": 0.0,
      "shopify_orders": 0,
      "revenue_source": "meta_pixel",
      "cac": 0,
      "roas": 0.0,
      "ctr": 0.0
    },
    {
      "region": "Central Luzon",
      "reach": 1,
      "clicks": 0,
      "impressions": 2,
      "spend": 0.03,
      "purchases": 0,
      "revenue": 0.0,
      "shopify_orders": 0,
      "revenue_source": "meta_pixel",
      "cac": 0,
      "roas": 0.0,
      "ctr": 0.0
    },
    {
      "region": "Al Khor",
      "reach": 1,
      "clicks": 0,
      "impressions": 1,
      "spend": 0.01,
      "purchases": 0,
      "revenue": 0.0,
      "shopify_orders": 0,
      "revenue_source": "meta_pixel",
      "cac": 0,
      "roas": 0.0,
      "ctr": 0.0
    },
    {
      "region": "Alabama",
      "reach": 1,
      "clicks": 0,
      "impressions": 1,
      "spend": 0.01,
      "purchases": 0,
      "revenue": 0.0,
      "shopify_orders": 0,
      "revenue_source": "meta_pixel",
      "cac": 0,
      "roas": 0.0,
      "ctr": 0.0
    },
    {
      "region": "Bagmati Zone",
      "reach": 1,
      "clicks": 0,
      "impressions": 1,
      "spend": 0.01,
      "purchases": 0,
      "revenue": 0.0,
      "shopify_orders": 0,
      "revenue_source": "meta_pixel",
      "cac": 0,
      "roas": 0.0,
      "ctr": 0.0
    }
  ],
  "placements": [
    {
      "platform": "facebook",
      "position": "feed",
      "spend": 534795.26,
      "impressions": 2827861,
      "clicks": 58226,
      "reach": 1218618,
      "purchases": 792,
      "revenue": 728767.23,
      "cac": 675.25,
      "ctr": 2.06,
      "roas": 1.36
    },
    {
      "platform": "instagram",
      "position": "feed",
      "spend": 494163.68,
      "impressions": 4271278,
      "clicks": 24021,
      "reach": 2690711,
      "purchases": 732,
      "revenue": 705998.79,
      "cac": 675.09,
      "ctr": 0.56,
      "roas": 1.43
    },
    {
      "platform": "instagram",
      "position": "instagram_reels",
      "spend": 459312.8,
      "impressions": 6207109,
      "clicks": 32492,
      "reach": 3576354,
      "purchases": 731,
      "revenue": 645714.05,
      "cac": 628.33,
      "ctr": 0.52,
      "roas": 1.41
    },
    {
      "platform": "facebook",
      "position": "facebook_reels",
      "spend": 361573.51,
      "impressions": 2391823,
      "clicks": 33164,
      "reach": 795059,
      "purchases": 572,
      "revenue": 478444.86,
      "cac": 632.12,
      "ctr": 1.39,
      "roas": 1.32
    },
    {
      "platform": "instagram",
      "position": "instagram_stories",
      "spend": 138896.47,
      "impressions": 692045,
      "clicks": 11437,
      "reach": 371922,
      "purchases": 211,
      "revenue": 186843.3,
      "cac": 658.28,
      "ctr": 1.65,
      "roas": 1.35
    },
    {
      "platform": "facebook",
      "position": "facebook_stories",
      "spend": 54163.12,
      "impressions": 107297,
      "clicks": 3594,
      "reach": 55133,
      "purchases": 62,
      "revenue": 49428.0,
      "cac": 873.6,
      "ctr": 3.35,
      "roas": 0.91
    },
    {
      "platform": "audience_network",
      "position": "rewarded_video",
      "spend": 19122.14,
      "impressions": 60342,
      "clicks": 13557,
      "reach": 7652,
      "purchases": 22,
      "revenue": 23921.5,
      "cac": 869.19,
      "ctr": 22.47,
      "roas": 1.25
    },
    {
      "platform": "audience_network",
      "position": "an_classic",
      "spend": 16940.85,
      "impressions": 62902,
      "clicks": 11062,
      "reach": 9651,
      "purchases": 21,
      "revenue": 22755.0,
      "cac": 806.71,
      "ctr": 17.59,
      "roas": 1.34
    },
    {
      "platform": "facebook",
      "position": "instream_video",
      "spend": 11231.37,
      "impressions": 85864,
      "clicks": 1479,
      "reach": 22002,
      "purchases": 19,
      "revenue": 19254.55,
      "cac": 591.12,
      "ctr": 1.72,
      "roas": 1.71
    },
    {
      "platform": "threads",
      "position": "threads_feed",
      "spend": 4102.76,
      "impressions": 105198,
      "clicks": 1136,
      "reach": 79818,
      "purchases": 4,
      "revenue": 3222.0,
      "cac": 1025.69,
      "ctr": 1.08,
      "roas": 0.79
    },
    {
      "platform": "facebook",
      "position": "marketplace",
      "spend": 2384.26,
      "impressions": 20404,
      "clicks": 222,
      "reach": 8486,
      "purchases": 8,
      "revenue": 8844.07,
      "cac": 298.03,
      "ctr": 1.09,
      "roas": 3.71
    },
    {
      "platform": "facebook",
      "position": "facebook_reels_overlay",
      "spend": 1712.04,
      "impressions": 46013,
      "clicks": 275,
      "reach": 10337,
      "purchases": 6,
      "revenue": 6348.55,
      "cac": 285.34,
      "ctr": 0.6,
      "roas": 3.71
    },
    {
      "platform": "instagram",
      "position": "instagram_explore_grid_home",
      "spend": 1270.69,
      "impressions": 368375,
      "clicks": 97,
      "reach": 342541,
      "purchases": 3,
      "revenue": 1859.0,
      "cac": 423.56,
      "ctr": 0.03,
      "roas": 1.46
    },
    {
      "platform": "facebook",
      "position": "search",
      "spend": 1016.17,
      "impressions": 4930,
      "clicks": 85,
      "reach": 4328,
      "purchases": 4,
      "revenue": 4148.0,
      "cac": 254.04,
      "ctr": 1.72,
      "roas": 4.08
    },
    {
      "platform": "facebook",
      "position": "facebook_notification",
      "spend": 1010.65,
      "impressions": 2568,
      "clicks": 127,
      "reach": 1626,
      "purchases": 2,
      "revenue": 2516.5,
      "cac": 505.32,
      "ctr": 4.95,
      "roas": 2.49
    },
    {
      "platform": "whatsapp",
      "position": "status",
      "spend": 827.83,
      "impressions": 890644,
      "clicks": 2965,
      "reach": 3179,
      "purchases": 0,
      "revenue": 0.0,
      "cac": 0,
      "ctr": 0.33,
      "roas": 0.0
    },
    {
      "platform": "facebook",
      "position": "facebook_profile_feed",
      "spend": 724.37,
      "impressions": 5777,
      "clicks": 77,
      "reach": 5233,
      "purchases": 0,
      "revenue": 0.0,
      "cac": 0,
      "ctr": 1.33,
      "roas": 0.0
    },
    {
      "platform": "facebook",
      "position": "right_hand_column",
      "spend": 528.58,
      "impressions": 16981,
      "clicks": 15,
      "reach": 3029,
      "purchases": 2,
      "revenue": 1250.0,
      "cac": 264.29,
      "ctr": 0.09,
      "roas": 2.36
    },
    {
      "platform": "instagram",
      "position": "instagram_explore",
      "spend": 213.01,
      "impressions": 1895,
      "clicks": 13,
      "reach": 1337,
      "purchases": 0,
      "revenue": 0.0,
      "cac": 0,
      "ctr": 0.69,
      "roas": 0.0
    },
    {
      "platform": "instagram",
      "position": "instagram_search",
      "spend": 58.78,
      "impressions": 3316,
      "clicks": 7,
      "reach": 3260,
      "purchases": 0,
      "revenue": 0.0,
      "cac": 0,
      "ctr": 0.21,
      "roas": 0.0
    },
    {
      "platform": "facebook",
      "position": "biz_disco_feed",
      "spend": 35.78,
      "impressions": 127,
      "clicks": 1,
      "reach": 96,
      "purchases": 0,
      "revenue": 0.0,
      "cac": 0,
      "ctr": 0.79,
      "roas": 0.0
    },
    {
      "platform": "messenger",
      "position": "messenger_stories",
      "spend": 2.24,
      "impressions": 34,
      "clicks": 0,
      "reach": 34,
      "purchases": 0,
      "revenue": 0.0,
      "cac": 0,
      "ctr": 0.0,
      "roas": 0.0
    },
    {
      "platform": "unknown",
      "position": "unknown",
      "spend": 0.06,
      "impressions": 1,
      "clicks": 0,
      "reach": 1,
      "purchases": 1,
      "revenue": 630.0,
      "cac": 0.06,
      "ctr": 0.0,
      "roas": 10500.0
    }
  ],
  "hours": [
    {
      "hour": "00",
      "spend": 21878.3,
      "impressions": 161047,
      "clicks": 2002,
      "purchases": 39,
      "cac": 560.98
    },
    {
      "hour": "01",
      "spend": 12214.17,
      "impressions": 84263,
      "clicks": 1081,
      "purchases": 17,
      "cac": 718.48
    },
    {
      "hour": "02",
      "spend": 6265.52,
      "impressions": 42847,
      "clicks": 549,
      "purchases": 9,
      "cac": 696.17
    },
    {
      "hour": "03",
      "spend": 3783.01,
      "impressions": 23542,
      "clicks": 305,
      "purchases": 3,
      "cac": 1261.0
    },
    {
      "hour": "04",
      "spend": 3452.23,
      "impressions": 17571,
      "clicks": 288,
      "purchases": 8,
      "cac": 431.53
    },
    {
      "hour": "05",
      "spend": 4695.9,
      "impressions": 23069,
      "clicks": 308,
      "purchases": 3,
      "cac": 1565.3
    },
    {
      "hour": "06",
      "spend": 8300.65,
      "impressions": 51112,
      "clicks": 532,
      "purchases": 7,
      "cac": 1185.81
    },
    {
      "hour": "07",
      "spend": 15387.53,
      "impressions": 109139,
      "clicks": 1024,
      "purchases": 18,
      "cac": 854.86
    },
    {
      "hour": "08",
      "spend": 21880.08,
      "impressions": 156994,
      "clicks": 1559,
      "purchases": 28,
      "cac": 781.43
    },
    {
      "hour": "09",
      "spend": 26316.97,
      "impressions": 173642,
      "clicks": 1905,
      "purchases": 32,
      "cac": 822.41
    },
    {
      "hour": "10",
      "spend": 27958.8,
      "impressions": 194056,
      "clicks": 2112,
      "purchases": 40,
      "cac": 698.97
    },
    {
      "hour": "11",
      "spend": 28634.6,
      "impressions": 204268,
      "clicks": 2361,
      "purchases": 46,
      "cac": 622.49
    },
    {
      "hour": "12",
      "spend": 29624.19,
      "impressions": 218097,
      "clicks": 2456,
      "purchases": 74,
      "cac": 400.33
    },
    {
      "hour": "13",
      "spend": 29609.38,
      "impressions": 233147,
      "clicks": 2769,
      "purchases": 58,
      "cac": 510.51
    },
    {
      "hour": "14",
      "spend": 30082.34,
      "impressions": 237545,
      "clicks": 2755,
      "purchases": 48,
      "cac": 626.72
    },
    {
      "hour": "15",
      "spend": 30886.0,
      "impressions": 233778,
      "clicks": 2917,
      "purchases": 57,
      "cac": 541.86
    },
    {
      "hour": "16",
      "spend": 31536.34,
      "impressions": 239563,
      "clicks": 2970,
      "purchases": 47,
      "cac": 670.99
    },
    {
      "hour": "17",
      "spend": 29876.61,
      "impressions": 230709,
      "clicks": 2692,
      "purchases": 51,
      "cac": 585.82
    },
    {
      "hour": "18",
      "spend": 29099.15,
      "impressions": 228757,
      "clicks": 2728,
      "purchases": 52,
      "cac": 559.6
    },
    {
      "hour": "19",
      "spend": 28125.92,
      "impressions": 229978,
      "clicks": 2696,
      "purchases": 52,
      "cac": 540.88
    },
    {
      "hour": "20",
      "spend": 28204.45,
      "impressions": 234940,
      "clicks": 2879,
      "purchases": 42,
      "cac": 671.53
    },
    {
      "hour": "21",
      "spend": 30037.35,
      "impressions": 271632,
      "clicks": 3112,
      "purchases": 42,
      "cac": 715.17
    },
    {
      "hour": "22",
      "spend": 31685.25,
      "impressions": 284741,
      "clicks": 3329,
      "purchases": 50,
      "cac": 633.71
    },
    {
      "hour": "23",
      "spend": 27179.8,
      "impressions": 233935,
      "clicks": 2758,
      "purchases": 37,
      "cac": 734.59
    }
  ],
  "pacing": {
    "days_elapsed": 3,
    "days_remaining": 27,
    "spend_to_date": 2104087.23,
    "daily_avg": 701362.41,
    "projected_month": 21040872.3,
    "purchases_to_date": 3192,
    "projected_purchases": 31920,
    "projected_cac": 659.18
  },
  "lastUpdated": "2026-04-03 12:42 UTC",
  "dateRange": "last_28d",
  "shopify_connected": true
}